{"data":[{"rank":"1","bib":"691","first_name":"Robert","last_name":"Fairbanks","gender_pos":"1","chip_time":"00:39:10","gender":"Male","finish_time":"00:39:10","club":null},{"rank":"2","bib":"2414","first_name":"Andrew","last_name":"Duke","gender_pos":"2","chip_time":"00:39:23","gender":"Male","finish_time":"00:39:24","club":null},{"rank":"3","bib":"2427","first_name":"Oliver","last_name":"Cwikowski","gender_pos":"3","chip_time":"00:39:15","gender":"Male","finish_time":"00:39:26","club":"Run Wild Mcr"},{"rank":"4","bib":"5378","first_name":"Tom","last_name":"Jackson","gender_pos":"4","chip_time":"00:39:28","gender":"Male","finish_time":"00:39:32","club":null},{"rank":"5","bib":"1468","first_name":"Robert","last_name":"Eendebak","gender_pos":"5","chip_time":"00:39:34","gender":"Male","finish_time":"00:39:43","club":"Run Wild Mcr"},{"rank":"6","bib":"776","first_name":"Robert","last_name":"Wadsworth","gender_pos":"6","chip_time":"00:39:57","gender":"Male","finish_time":"00:39:59","club":null},{"rank":"7","bib":"1148","first_name":"Savvas","last_name":"Zamboglou","gender_pos":"7","chip_time":"00:40:44","gender":"Male","finish_time":"00:40:48","club":null},{"rank":"8","bib":"2272","first_name":"Ciaran","last_name":"McManus","gender_pos":"8","chip_time":"00:40:58","gender":"Male","finish_time":"00:40:59","club":null},{"rank":"9","bib":"804","first_name":"Eamonn","last_name":"Dinan","gender_pos":"9","chip_time":"00:41:00","gender":"Male","finish_time":"00:41:04","club":null},{"rank":"10","bib":"1165","first_name":"Simon","last_name":"Phillips","gender_pos":"10","chip_time":"00:41:09","gender":"Male","finish_time":"00:41:14","club":null},{"rank":"11","bib":"2399","first_name":"Paul","last_name":"Moore","gender_pos":"11","chip_time":"00:41:35","gender":"Male","finish_time":"00:41:36","club":null},{"rank":"12","bib":"872","first_name":"Chris","last_name":"Ainsworth","gender_pos":"12","chip_time":"00:41:39","gender":"Male","finish_time":"00:41:41","club":null},{"rank":"13","bib":"1471","first_name":"Paul","last_name":"Smith","gender_pos":"13","chip_time":"00:41:47","gender":"Male","finish_time":"00:41:48","club":null},{"rank":"14","bib":"2278","first_name":"Amy-Rose","last_name":"Cauley","gender_pos":"1","chip_time":"00:41:42","gender":"Female","finish_time":"00:41:49","club":null},{"rank":"15","bib":"2462","first_name":"Bradley","last_name":"Dickerson","gender_pos":"14","chip_time":"00:41:54","gender":"Male","finish_time":"00:41:56","club":null},{"rank":"16","bib":"2446","first_name":"Simon","last_name":"Clarke","gender_pos":"15","chip_time":"00:42:09","gender":"Male","finish_time":"00:42:12","club":"Team Kratos"},{"rank":"17","bib":"1346","first_name":"Jon","last_name":"Evans","gender_pos":"16","chip_time":"00:42:19","gender":"Male","finish_time":"00:42:21","club":null},{"rank":"18","bib":"956","first_name":"Ben","last_name":"Roberts","gender_pos":"17","chip_time":"00:42:24","gender":"Male","finish_time":"00:42:31","club":"Astrazeneca It"},{"rank":"19","bib":"2385","first_name":"Adam","last_name":"Selby","gender_pos":"18","chip_time":"00:42:25","gender":"Male","finish_time":"00:42:33","club":null},{"rank":"20","bib":"2434","first_name":"Lee","last_name":"Whitehouse","gender_pos":"19","chip_time":"00:42:35","gender":"Male","finish_time":"00:42:38","club":"Smooth Radio 10k"},{"rank":"21","bib":"864","first_name":"Kev","last_name":"Logue","gender_pos":"20","chip_time":"00:42:38","gender":"Male","finish_time":"00:42:42","club":null},{"rank":"22","bib":"2018","first_name":"Greg","last_name":"Ellam","gender_pos":"21","chip_time":"00:42:42","gender":"Male","finish_time":"00:42:44","club":null},{"rank":"23","bib":"748","first_name":"Joshua","last_name":"Strange","gender_pos":"22","chip_time":"00:42:35","gender":"Male","finish_time":"00:42:50","club":null},{"rank":"24","bib":"940","first_name":"Andy","last_name":"Thorp","gender_pos":"23","chip_time":"00:43:07","gender":"Male","finish_time":"00:43:10","club":"Astrazeneca It"},{"rank":"25","bib":"1177","first_name":"Andrew","last_name":"Frazer","gender_pos":"24","chip_time":"00:43:04","gender":"Male","finish_time":"00:43:11","club":null},{"rank":"26","bib":"2054","first_name":"Jonathan","last_name":"Eagle","gender_pos":"25","chip_time":"00:43:21","gender":"Male","finish_time":"00:43:23","club":null},{"rank":"27","bib":"1354","first_name":"Luke","last_name":"Rowe","gender_pos":"26","chip_time":"00:43:22","gender":"Male","finish_time":"00:43:26","club":null},{"rank":"28","bib":"1028","first_name":"Girish","last_name":"Patel","gender_pos":"27","chip_time":"00:43:28","gender":"Male","finish_time":"00:43:38","club":"Under Trained & Overconfident"},{"rank":"29","bib":"1025","first_name":"Stephen","last_name":"Parnell","gender_pos":"28","chip_time":"00:43:28","gender":"Male","finish_time":"00:43:38","club":"Under Trained & Overconfident"},{"rank":"30","bib":"5369","first_name":"Benoit","last_name":"Carpenter","gender_pos":"29","chip_time":"00:43:41","gender":"Male","finish_time":"00:43:44","club":null},{"rank":"31","bib":"817","first_name":"Callum","last_name":"Crosby","gender_pos":"30","chip_time":"00:43:44","gender":"Male","finish_time":"00:43:46","club":null},{"rank":"32","bib":"2057","first_name":"Pierre","last_name":"O Conghaile","gender_pos":"31","chip_time":"00:43:29","gender":"Male","finish_time":"00:43:49","club":"Accenture"},{"rank":"33","bib":"1171","first_name":"David","last_name":"Addiscott","gender_pos":"32","chip_time":"00:43:38","gender":"Male","finish_time":"00:43:50","club":null},{"rank":"34","bib":"2019","first_name":"Natalia","last_name":"Perez Castellanos","gender_pos":"2","chip_time":"00:43:49","gender":"Female","finish_time":"00:43:52","club":null},{"rank":"35","bib":"689","first_name":"John","last_name":"McLoughlin","gender_pos":"33","chip_time":"00:43:55","gender":"Male","finish_time":"00:43:56","club":null},{"rank":"36","bib":"2269","first_name":"Gerard","last_name":"Forde","gender_pos":"34","chip_time":"00:43:56","gender":"Male","finish_time":"00:43:58","club":null},{"rank":"37","bib":"896","first_name":"Colin","last_name":"Bebbington","gender_pos":"35","chip_time":"00:43:13","gender":"Male","finish_time":"00:43:59","club":null},{"rank":"38","bib":"1173","first_name":"Alex","last_name":"Hurley","gender_pos":"36","chip_time":"00:43:59","gender":"Male","finish_time":"00:44:05","club":null},{"rank":"39","bib":"741","first_name":"Darren","last_name":"Preston","gender_pos":"37","chip_time":"00:44:07","gender":"Male","finish_time":"00:44:08","club":null},{"rank":"40","bib":"1042","first_name":"Chris","last_name":"Mower","gender_pos":"38","chip_time":"00:43:23","gender":"Male","finish_time":"00:44:09","club":"Waters Uk - North"},{"rank":"41","bib":"1343","first_name":"James","last_name":"Willard","gender_pos":"39","chip_time":"00:43:20","gender":"Male","finish_time":"00:44:12","club":null},{"rank":"42","bib":"2464","first_name":"Niall","last_name":"Patton","gender_pos":"40","chip_time":"00:43:19","gender":"Male","finish_time":"00:44:12","club":null},{"rank":"43","bib":"944","first_name":"Andy","last_name":"Bennett","gender_pos":"41","chip_time":"00:44:12","gender":"Male","finish_time":"00:44:15","club":"Astrazeneca It"},{"rank":"44","bib":"906","first_name":"Mike","last_name":"Race","gender_pos":"42","chip_time":"00:44:17","gender":"Male","finish_time":"00:44:22","club":null},{"rank":"45","bib":"2378","first_name":"Scott","last_name":"Lally","gender_pos":"43","chip_time":"00:44:17","gender":"Male","finish_time":"00:44:23","club":null},{"rank":"46","bib":"865","first_name":"Melanie","last_name":"Barber","gender_pos":"3","chip_time":"00:44:24","gender":"Female","finish_time":"00:44:29","club":null},{"rank":"47","bib":"2042","first_name":"Rob","last_name":"Marsden","gender_pos":"44","chip_time":"00:44:27","gender":"Male","finish_time":"00:44:29","club":null},{"rank":"48","bib":"2051","first_name":"Bastien","last_name":"Peyronnel","gender_pos":"45","chip_time":"00:44:28","gender":"Male","finish_time":"00:44:31","club":null},{"rank":"49","bib":"2017","first_name":"Abder","last_name":"Mokhbat","gender_pos":"46","chip_time":"00:44:35","gender":"Male","finish_time":"00:44:37","club":null},{"rank":"50","bib":"2069","first_name":"Mark","last_name":"Harrison","gender_pos":"47","chip_time":"00:44:35","gender":"Male","finish_time":"00:44:46","club":"Run Wild Mcr"},{"rank":"51","bib":"668","first_name":"Mr G P","last_name":"Demaine","gender_pos":"48","chip_time":"00:44:46","gender":"Male","finish_time":"00:44:49","club":null},{"rank":"52","bib":"842","first_name":"James","last_name":"Rees","gender_pos":"49","chip_time":"00:44:36","gender":"Male","finish_time":"00:44:51","club":null},{"rank":"53","bib":"840","first_name":"Suze","last_name":"Pentland","gender_pos":"4","chip_time":"00:44:36","gender":"Female","finish_time":"00:44:51","club":null},{"rank":"54","bib":"2072","first_name":"Shona","last_name":"O' Flynn","gender_pos":"5","chip_time":"00:44:43","gender":"Female","finish_time":"00:44:54","club":"Run Wild Mcr"},{"rank":"55","bib":"2426","first_name":"Joe","last_name":"Blakey","gender_pos":"50","chip_time":"00:44:48","gender":"Male","finish_time":"00:44:59","club":"Run Wild Mcr"},{"rank":"56","bib":"1683","first_name":"Mark","last_name":"Carlin","gender_pos":"51","chip_time":"00:44:45","gender":"Male","finish_time":"00:45:00","club":null},{"rank":"57","bib":"1684","first_name":"Richard","last_name":"Leece","gender_pos":"52","chip_time":"00:44:59","gender":"Male","finish_time":"00:45:00","club":null},{"rank":"58","bib":"652","first_name":"Tom","last_name":"Higham","gender_pos":"53","chip_time":"00:44:52","gender":"Male","finish_time":"00:45:07","club":null},{"rank":"59","bib":"2382","first_name":"Philip","last_name":"Hurst","gender_pos":"54","chip_time":"00:45:09","gender":"Male","finish_time":"00:45:13","club":null},{"rank":"60","bib":"2416","first_name":"David","last_name":"Brady","gender_pos":"55","chip_time":"00:45:14","gender":"Male","finish_time":"00:45:18","club":null},{"rank":"61","bib":"847","first_name":"Mohammed","last_name":"Rizwan","gender_pos":"56","chip_time":"00:45:11","gender":"Male","finish_time":"00:45:24","club":null},{"rank":"62","bib":"961","first_name":"Richard","last_name":"Francis","gender_pos":"57","chip_time":"00:45:13","gender":"Male","finish_time":"00:45:25","club":"Blackpool Donkeys"},{"rank":"63","bib":"939","first_name":"Jonathan","last_name":"Charles","gender_pos":"58","chip_time":"00:45:23","gender":"Male","finish_time":"00:45:31","club":"Astrazeneca It"},{"rank":"64","bib":"1332","first_name":"Amy","last_name":"Welch","gender_pos":"6","chip_time":"00:45:25","gender":"Female","finish_time":"00:45:35","club":null},{"rank":"65","bib":"1369","first_name":"William","last_name":"Keeling","gender_pos":"59","chip_time":"00:45:22","gender":"Male","finish_time":"00:45:35","club":null},{"rank":"66","bib":"5381","first_name":"Chris","last_name":"Earle","gender_pos":"60","chip_time":"00:45:34","gender":"Male","finish_time":"00:45:36","club":null},{"rank":"67","bib":"2410","first_name":"Jack","last_name":"Bond","gender_pos":"61","chip_time":"00:45:13","gender":"Male","finish_time":"00:45:42","club":null},{"rank":"68","bib":"2440","first_name":"Gemma","last_name":"Mainprize","gender_pos":"7","chip_time":"00:45:41","gender":"Female","finish_time":"00:45:44","club":"Smooth Radio 10k"},{"rank":"69","bib":"2412","first_name":"Kevin","last_name":"Coughlan","gender_pos":"62","chip_time":"00:45:26","gender":"Male","finish_time":"00:45:44","club":null},{"rank":"70","bib":"2256","first_name":"Harry","last_name":"McDonald","gender_pos":"63","chip_time":"00:45:34","gender":"Male","finish_time":"00:45:46","club":"Run Wild Mcr"},{"rank":"71","bib":"1365","first_name":"Tariq","last_name":"Ahmed","gender_pos":"64","chip_time":"00:45:24","gender":"Male","finish_time":"00:45:46","club":null},{"rank":"72","bib":"2023","first_name":"Neil","last_name":"Ryan","gender_pos":"65","chip_time":"00:44:56","gender":"Male","finish_time":"00:45:47","club":null},{"rank":"73","bib":"1162","first_name":"Chris","last_name":"Daniels","gender_pos":"66","chip_time":"00:45:46","gender":"Male","finish_time":"00:45:48","club":null},{"rank":"74","bib":"871","first_name":"Gillian","last_name":"Doolan","gender_pos":"8","chip_time":"00:45:55","gender":"Female","finish_time":"00:46:00","club":null},{"rank":"75","bib":"715","first_name":"David","last_name":"Blakemore","gender_pos":"67","chip_time":"00:45:57","gender":"Male","finish_time":"00:46:02","club":null},{"rank":"76","bib":"2267","first_name":"Scott","last_name":"Taylor","gender_pos":"68","chip_time":"00:45:32","gender":"Male","finish_time":"00:46:15","club":null},{"rank":"77","bib":"1364","first_name":"Stuart","last_name":"Rogers","gender_pos":"69","chip_time":"00:46:09","gender":"Male","finish_time":"00:46:15","club":null},{"rank":"78","bib":"1451","first_name":"Andrew","last_name":"Robbins","gender_pos":"70","chip_time":"00:45:59","gender":"Male","finish_time":"00:46:15","club":null},{"rank":"79","bib":"4781","first_name":"George","last_name":"Clifford","gender_pos":"71","chip_time":"00:45:32","gender":"Male","finish_time":"00:46:16","club":null},{"rank":"80","bib":"1139","first_name":"William","last_name":"Carter","gender_pos":"72","chip_time":"00:46:03","gender":"Male","finish_time":"00:46:22","club":null},{"rank":"81","bib":"680","first_name":"Paul","last_name":"Rutter","gender_pos":"73","chip_time":"00:46:19","gender":"Male","finish_time":"00:46:23","club":null},{"rank":"82","bib":"4605","first_name":"Asha","last_name":"Agarwal","gender_pos":"9","chip_time":"00:46:22","gender":"Female","finish_time":"00:46:24","club":"Astrazeneca It"},{"rank":"83","bib":"2369","first_name":"Aj","last_name":"Lockington","gender_pos":"74","chip_time":"00:45:56","gender":"Male","finish_time":"00:46:25","club":"Roger Bannister'S Long Lost Co"},{"rank":"84","bib":"984","first_name":"Tom","last_name":"Norfolk","gender_pos":"75","chip_time":"00:46:09","gender":"Male","finish_time":"00:46:25","club":"Coffee Drinkers Who Run"},{"rank":"85","bib":"888","first_name":"Peter","last_name":"Billcliff","gender_pos":"76","chip_time":"00:45:52","gender":"Male","finish_time":"00:46:28","club":null},{"rank":"86","bib":"1372","first_name":"Mark","last_name":"Skelton","gender_pos":"77","chip_time":"00:46:05","gender":"Male","finish_time":"00:46:30","club":"Bolton Bulls"},{"rank":"87","bib":"2275","first_name":"Shaun","last_name":"Tunstall","gender_pos":"78","chip_time":"00:46:33","gender":"Male","finish_time":"00:46:36","club":null},{"rank":"88","bib":"2025","first_name":"Jacob","last_name":"Parkes","gender_pos":"79","chip_time":"00:46:36","gender":"Male","finish_time":"00:46:37","club":null},{"rank":"89","bib":"1459","first_name":"Sean","last_name":"Clark","gender_pos":"80","chip_time":"00:46:29","gender":"Male","finish_time":"00:46:38","club":null},{"rank":"90","bib":"820","first_name":"Bal\u00e1zs","last_name":"Babarczi","gender_pos":"81","chip_time":"00:46:40","gender":"Male","finish_time":"00:46:47","club":null},{"rank":"91","bib":"709","first_name":"Andrew","last_name":"Holland","gender_pos":"82","chip_time":"00:46:25","gender":"Male","finish_time":"00:46:49","club":null},{"rank":"92","bib":"667","first_name":"Jonathan","last_name":"Crossfield","gender_pos":"83","chip_time":"00:46:44","gender":"Male","finish_time":"00:46:50","club":null},{"rank":"93","bib":"932","first_name":"Steven","last_name":"Kirby","gender_pos":"84","chip_time":"00:46:25","gender":"Male","finish_time":"00:46:52","club":"#Teams23"},{"rank":"94","bib":"909","first_name":"Patrick","last_name":"Hagg","gender_pos":"85","chip_time":"00:46:29","gender":"Male","finish_time":"00:46:54","club":null},{"rank":"95","bib":"2465","first_name":"James","last_name":"Williams","gender_pos":"86","chip_time":"00:46:48","gender":"Male","finish_time":"00:47:01","club":null},{"rank":"96","bib":"1038","first_name":"Aaron","last_name":"Denevon","gender_pos":"87","chip_time":"00:46:23","gender":"Male","finish_time":"00:47:05","club":"Warby'S Warriors"},{"rank":"97","bib":"2034","first_name":"Harry","last_name":"Knight","gender_pos":"88","chip_time":"00:46:51","gender":"Male","finish_time":"00:47:07","club":null},{"rank":"98","bib":"1029","first_name":"Richard","last_name":"Warburton","gender_pos":"89","chip_time":"00:46:23","gender":"Male","finish_time":"00:47:07","club":"Warby'S Warriors"},{"rank":"99","bib":"1170","first_name":"Helen","last_name":"Sweeney","gender_pos":"10","chip_time":"00:46:17","gender":"Female","finish_time":"00:47:08","club":null},{"rank":"100","bib":"879","first_name":"Jamie","last_name":"Lynch","gender_pos":"90","chip_time":"00:47:07","gender":"Male","finish_time":"00:47:09","club":null},{"rank":"101","bib":"1004","first_name":"Tom","last_name":"Gill","gender_pos":"91","chip_time":"00:46:34","gender":"Male","finish_time":"00:47:09","club":"Straight Outta Crompton"},{"rank":"102","bib":"770","first_name":"Ximena","last_name":"Schmidt","gender_pos":"11","chip_time":"00:46:23","gender":"Female","finish_time":"00:47:10","club":null},{"rank":"103","bib":"1160","first_name":"Giles","last_name":"Orr-Ewing","gender_pos":"92","chip_time":"00:46:27","gender":"Male","finish_time":"00:47:10","club":null},{"rank":"104","bib":"1147","first_name":"Andy","last_name":"Hayes","gender_pos":"93","chip_time":"00:47:08","gender":"Male","finish_time":"00:47:11","club":null},{"rank":"105","bib":"2373","first_name":"Jeff","last_name":"Day","gender_pos":"94","chip_time":"00:46:56","gender":"Male","finish_time":"00:47:14","club":"Northwich Running Club"},{"rank":"106","bib":"1159","first_name":"Hugo","last_name":"Samengo-Turner","gender_pos":"95","chip_time":"00:46:32","gender":"Male","finish_time":"00:47:16","club":null},{"rank":"107","bib":"2388","first_name":"Andrew","last_name":"Gawthorpe","gender_pos":"96","chip_time":"00:46:25","gender":"Male","finish_time":"00:47:17","club":null},{"rank":"108","bib":"767","first_name":"Mark","last_name":"Rigby","gender_pos":"97","chip_time":"00:46:44","gender":"Male","finish_time":"00:47:20","club":null},{"rank":"109","bib":"2384","first_name":"Barry","last_name":"Heap","gender_pos":"98","chip_time":"00:47:15","gender":"Male","finish_time":"00:47:20","club":null},{"rank":"110","bib":"1001","first_name":"Mike","last_name":"Turner","gender_pos":"99","chip_time":"00:46:46","gender":"Male","finish_time":"00:47:22","club":"Straight Outta Crompton"},{"rank":"111","bib":"844","first_name":"Craig","last_name":"Holland","gender_pos":"100","chip_time":"00:47:10","gender":"Male","finish_time":"00:47:25","club":null},{"rank":"112","bib":"919","first_name":"Mark","last_name":"Froggatt","gender_pos":"101","chip_time":"00:47:17","gender":"Male","finish_time":"00:47:26","club":null},{"rank":"113","bib":"2041","first_name":"Declan","last_name":"Sealy","gender_pos":"102","chip_time":"00:46:36","gender":"Male","finish_time":"00:47:28","club":null},{"rank":"114","bib":"1015","first_name":"Robert","last_name":"Rowbotham","gender_pos":"103","chip_time":"00:47:25","gender":"Male","finish_time":"00:47:32","club":"Team Squire Pb"},{"rank":"115","bib":"732","first_name":"George","last_name":"Hurford","gender_pos":"104","chip_time":"00:47:33","gender":"Male","finish_time":"00:47:38","club":null},{"rank":"116","bib":"874","first_name":"David","last_name":"Reid","gender_pos":"105","chip_time":"00:47:02","gender":"Male","finish_time":"00:47:39","club":null},{"rank":"117","bib":"653","first_name":"Mark","last_name":"Brett","gender_pos":"106","chip_time":"00:47:35","gender":"Male","finish_time":"00:47:41","club":null},{"rank":"118","bib":"687","first_name":"Mike","last_name":"Bent","gender_pos":"107","chip_time":"00:47:19","gender":"Male","finish_time":"00:47:46","club":null},{"rank":"119","bib":"660","first_name":"Adam","last_name":"Jones","gender_pos":"108","chip_time":"00:47:43","gender":"Male","finish_time":"00:47:49","club":null},{"rank":"120","bib":"1380","first_name":"James","last_name":"Hallam","gender_pos":"109","chip_time":"00:47:03","gender":"Male","finish_time":"00:47:49","club":"Waters Uk - North"},{"rank":"121","bib":"2409","first_name":"Jordan","last_name":"Crosse","gender_pos":"110","chip_time":"00:47:26","gender":"Male","finish_time":"00:47:55","club":null},{"rank":"122","bib":"2260","first_name":"Chris","last_name":"Poole","gender_pos":"111","chip_time":"00:47:57","gender":"Male","finish_time":"00:47:57","club":null},{"rank":"123","bib":"1141","first_name":"Duncan","last_name":"Robinson","gender_pos":"112","chip_time":"00:47:43","gender":"Male","finish_time":"00:47:59","club":null},{"rank":"124","bib":"778","first_name":"Felicity","last_name":"Nelson","gender_pos":"12","chip_time":"00:47:47","gender":"Female","finish_time":"00:48:00","club":null},{"rank":"125","bib":"1163","first_name":"Rob","last_name":"Collier","gender_pos":"113","chip_time":"00:47:48","gender":"Male","finish_time":"00:48:03","club":null},{"rank":"126","bib":"2258","first_name":"Steven","last_name":"Eccles","gender_pos":"114","chip_time":"00:47:53","gender":"Male","finish_time":"00:48:05","club":null},{"rank":"127","bib":"674","first_name":"James","last_name":"King","gender_pos":"115","chip_time":"00:47:48","gender":"Male","finish_time":"00:48:06","club":null},{"rank":"128","bib":"1374","first_name":"Damien","last_name":"Rafferty","gender_pos":"116","chip_time":"00:47:53","gender":"Male","finish_time":"00:48:11","club":"Tace"},{"rank":"129","bib":"935","first_name":"Kay","last_name":"Buckley","gender_pos":"13","chip_time":"00:47:48","gender":"Female","finish_time":"00:48:13","club":"#Teams23"},{"rank":"130","bib":"1341","first_name":"Graham","last_name":"Jordan","gender_pos":"117","chip_time":"00:48:11","gender":"Male","finish_time":"00:48:17","club":null},{"rank":"131","bib":"2454","first_name":"Steve","last_name":"Land","gender_pos":"118","chip_time":"00:47:56","gender":"Male","finish_time":"00:48:18","club":null},{"rank":"132","bib":"2415","first_name":"Nick","last_name":"Trott","gender_pos":"119","chip_time":"00:48:14","gender":"Male","finish_time":"00:48:20","club":null},{"rank":"133","bib":"5387","first_name":"Adam","last_name":"Cunningham","gender_pos":"120","chip_time":"00:48:16","gender":"Male","finish_time":"00:48:23","club":null},{"rank":"134","bib":"1142","first_name":"Edward","last_name":"Higgs","gender_pos":"121","chip_time":"00:48:08","gender":"Male","finish_time":"00:48:24","club":null},{"rank":"135","bib":"703","first_name":"Jane","last_name":"Maher","gender_pos":"14","chip_time":"00:48:24","gender":"Female","finish_time":"00:48:30","club":null},{"rank":"136","bib":"780","first_name":"Nick","last_name":"Morgan","gender_pos":"122","chip_time":"00:48:12","gender":"Male","finish_time":"00:48:33","club":null},{"rank":"137","bib":"1342","first_name":"Greg","last_name":"Dove","gender_pos":"123","chip_time":"00:48:16","gender":"Male","finish_time":"00:48:33","club":null},{"rank":"138","bib":"2428","first_name":"Melissa","last_name":"Metcalf","gender_pos":"15","chip_time":"00:48:23","gender":"Female","finish_time":"00:48:33","club":"Run Wild Mcr"},{"rank":"139","bib":"2026","first_name":"Stuart","last_name":"Phillips","gender_pos":"124","chip_time":"00:47:57","gender":"Male","finish_time":"00:48:33","club":null},{"rank":"140","bib":"947","first_name":"James","last_name":"Tweedy","gender_pos":"125","chip_time":"00:47:45","gender":"Male","finish_time":"00:48:34","club":"Astrazeneca It"},{"rank":"141","bib":"960","first_name":"Laura","last_name":"Butt","gender_pos":"16","chip_time":"00:48:32","gender":"Female","finish_time":"00:48:40","club":"Astrazeneca It"},{"rank":"142","bib":"1179","first_name":"Abder","last_name":"Mokhbat","gender_pos":"126","chip_time":"00:48:18","gender":"Male","finish_time":"00:48:41","club":null},{"rank":"143","bib":"2398","first_name":"Andrew","last_name":"Clarke","gender_pos":"127","chip_time":"00:48:22","gender":"Male","finish_time":"00:48:42","club":null},{"rank":"144","bib":"779","first_name":"Natalie","last_name":"Heginbotham","gender_pos":"17","chip_time":"00:48:24","gender":"Female","finish_time":"00:48:42","club":null},{"rank":"145","bib":"1019","first_name":"Mark","last_name":"Catney","gender_pos":"128","chip_time":"00:48:24","gender":"Male","finish_time":"00:48:49","club":"The Mash Dashers"},{"rank":"146","bib":"2050","first_name":"Marc","last_name":"Gordien","gender_pos":"129","chip_time":"00:48:48","gender":"Male","finish_time":"00:48:52","club":null},{"rank":"147","bib":"2381","first_name":"Ian","last_name":"Hough","gender_pos":"130","chip_time":"00:48:48","gender":"Male","finish_time":"00:48:53","club":null},{"rank":"148","bib":"2257","first_name":"Simon","last_name":"Hughes","gender_pos":"131","chip_time":"00:48:43","gender":"Male","finish_time":"00:48:56","club":null},{"rank":"149","bib":"2273","first_name":"Lee","last_name":"Harris","gender_pos":"132","chip_time":"00:48:50","gender":"Male","finish_time":"00:48:58","club":null},{"rank":"150","bib":"2037","first_name":"Jonathan","last_name":"Tremewan","gender_pos":"133","chip_time":"00:48:54","gender":"Male","finish_time":"00:49:06","club":null},{"rank":"151","bib":"2268","first_name":"Laura","last_name":"Middleton","gender_pos":"18","chip_time":"00:49:05","gender":"Female","finish_time":"00:49:08","club":null},{"rank":"152","bib":"2368","first_name":"Jon","last_name":"Bilsborough","gender_pos":"134","chip_time":"00:49:02","gender":"Male","finish_time":"00:49:12","club":"Wigan Council Running Club"},{"rank":"153","bib":"2376","first_name":"Melanie","last_name":"Forbes","gender_pos":"19","chip_time":"00:48:45","gender":"Female","finish_time":"00:49:13","club":null},{"rank":"154","bib":"2377","first_name":"Lewis","last_name":"McIntyre","gender_pos":"135","chip_time":"00:49:09","gender":"Male","finish_time":"00:49:15","club":null},{"rank":"155","bib":"806","first_name":"Andy","last_name":"Dooley","gender_pos":"136","chip_time":"00:49:15","gender":"Male","finish_time":"00:49:17","club":null},{"rank":"156","bib":"2071","first_name":"James","last_name":"Keitley","gender_pos":"137","chip_time":"00:48:48","gender":"Male","finish_time":"00:49:23","club":"Run Wild Mcr"},{"rank":"157","bib":"927","first_name":"Tom","last_name":"Lee","gender_pos":"138","chip_time":"00:49:13","gender":"Male","finish_time":"00:49:23","club":null},{"rank":"158","bib":"877","first_name":"Matt","last_name":"Joinson","gender_pos":"139","chip_time":"00:49:21","gender":"Male","finish_time":"00:49:26","club":null},{"rank":"159","bib":"954","first_name":"James","last_name":"Dyer","gender_pos":"140","chip_time":"00:49:20","gender":"Male","finish_time":"00:49:28","club":"Astrazeneca It"},{"rank":"160","bib":"1176","first_name":"Gregory","last_name":"Knowles","gender_pos":"141","chip_time":"00:49:21","gender":"Male","finish_time":"00:49:28","club":null},{"rank":"161","bib":"1467","first_name":"Micha&amp;#322&#59;","last_name":"Siennicki","gender_pos":"142","chip_time":"00:49:10","gender":"Male","finish_time":"00:49:29","club":null},{"rank":"162","bib":"1169","first_name":"Paul","last_name":"Carter","gender_pos":"143","chip_time":"00:49:29","gender":"Male","finish_time":"00:49:31","club":null},{"rank":"163","bib":"1144","first_name":"Peter","last_name":"Gregory","gender_pos":"144","chip_time":"00:49:29","gender":"Male","finish_time":"00:49:32","club":null},{"rank":"164","bib":"1368","first_name":"Victor","last_name":"Moran","gender_pos":"145","chip_time":"00:48:47","gender":"Male","finish_time":"00:49:36","club":null},{"rank":"165","bib":"735","first_name":"Steve","last_name":"Lillis","gender_pos":"146","chip_time":"00:49:09","gender":"Male","finish_time":"00:49:38","club":null},{"rank":"166","bib":"868","first_name":"Hadrian","last_name":"Lowe","gender_pos":"147","chip_time":"00:49:36","gender":"Male","finish_time":"00:49:40","club":null},{"rank":"167","bib":"1352","first_name":"Lee","last_name":"Mullan","gender_pos":"148","chip_time":"00:49:25","gender":"Male","finish_time":"00:49:43","club":null},{"rank":"168","bib":"1668","first_name":"Bob","last_name":"Allen","gender_pos":"149","chip_time":"00:49:35","gender":"Male","finish_time":"00:49:44","club":"Wigan Council Running Club"},{"rank":"169","bib":"2374","first_name":"Tony","last_name":"Clarke","gender_pos":"150","chip_time":"00:49:44","gender":"Male","finish_time":"00:49:53","club":"Wigan Council Running Club"},{"rank":"170","bib":"1149","first_name":"Stephen","last_name":"Langford","gender_pos":"151","chip_time":"00:49:39","gender":"Male","finish_time":"00:49:55","club":null},{"rank":"171","bib":"5379","first_name":"Alan","last_name":"Gray","gender_pos":"152","chip_time":"00:49:05","gender":"Male","finish_time":"00:49:58","club":null},{"rank":"172","bib":"870","first_name":"Derek","last_name":"Angus","gender_pos":"153","chip_time":"00:49:58","gender":"Male","finish_time":"00:50:02","club":null},{"rank":"173","bib":"705","first_name":"Peter","last_name":"Jones","gender_pos":"154","chip_time":"00:49:57","gender":"Male","finish_time":"00:50:10","club":null},{"rank":"174","bib":"1168","first_name":"Claire","last_name":"Atherton","gender_pos":"20","chip_time":"00:49:25","gender":"Female","finish_time":"00:50:17","club":null},{"rank":"175","bib":"2459","first_name":"Malcolm","last_name":"Smith","gender_pos":"155","chip_time":"00:50:11","gender":"Male","finish_time":"00:50:27","club":null},{"rank":"176","bib":"1156","first_name":"Nic","last_name":"Marko","gender_pos":"156","chip_time":"00:50:12","gender":"Male","finish_time":"00:50:29","club":null},{"rank":"177","bib":"724","first_name":"Russell","last_name":"Cox","gender_pos":"157","chip_time":"00:50:22","gender":"Male","finish_time":"00:50:33","club":null},{"rank":"178","bib":"2036","first_name":"Andrew","last_name":"Knight","gender_pos":"158","chip_time":"00:50:26","gender":"Male","finish_time":"00:50:38","club":null},{"rank":"179","bib":"2437","first_name":"Mark","last_name":"Lee","gender_pos":"159","chip_time":"00:49:54","gender":"Male","finish_time":"00:50:38","club":"Smooth Radio 10k"},{"rank":"180","bib":"997","first_name":"Christian","last_name":"Houghton","gender_pos":"160","chip_time":"00:50:07","gender":"Male","finish_time":"00:50:42","club":"Straight Outta Crompton"},{"rank":"181","bib":"1466","first_name":"Alan","last_name":"Fletcher","gender_pos":"161","chip_time":"00:50:44","gender":"Male","finish_time":"00:50:51","club":null},{"rank":"182","bib":"2413","first_name":"Benoit","last_name":"Carpentier","gender_pos":"162","chip_time":"00:50:36","gender":"Male","finish_time":"00:50:53","club":null},{"rank":"183","bib":"955","first_name":"Philip","last_name":"Tempest","gender_pos":"163","chip_time":"00:50:10","gender":"Male","finish_time":"00:50:58","club":"Astrazeneca It"},{"rank":"184","bib":"1046","first_name":"Richard","last_name":"Robinson","gender_pos":"164","chip_time":"00:50:11","gender":"Male","finish_time":"00:50:58","club":"Waters Uk - North"},{"rank":"185","bib":"1359","first_name":"Richard","last_name":"Green","gender_pos":"165","chip_time":"00:50:45","gender":"Male","finish_time":"00:51:09","club":null},{"rank":"186","bib":"1379","first_name":"Stephen","last_name":"Senior","gender_pos":"166","chip_time":"00:50:53","gender":"Male","finish_time":"00:51:12","club":"Tace"},{"rank":"187","bib":"2389","first_name":"Scott","last_name":"Fisher","gender_pos":"167","chip_time":"00:51:11","gender":"Male","finish_time":"00:51:21","club":null},{"rank":"188","bib":"1180","first_name":"Adam","last_name":"Lawson","gender_pos":"168","chip_time":"00:50:59","gender":"Male","finish_time":"00:51:26","club":"#Teams23"},{"rank":"189","bib":"794","first_name":"Carl","last_name":"Navarro","gender_pos":"169","chip_time":"00:51:19","gender":"Male","finish_time":"00:51:35","club":null},{"rank":"190","bib":"1461","first_name":"Elizabeth","last_name":"Sargent","gender_pos":"21","chip_time":"00:51:03","gender":"Female","finish_time":"00:51:36","club":null},{"rank":"191","bib":"2070","first_name":"Peter","last_name":"Hellawell","gender_pos":"170","chip_time":"00:51:02","gender":"Male","finish_time":"00:51:37","club":"Run Wild Mcr"},{"rank":"192","bib":"2016","first_name":"David","last_name":"Lowe","gender_pos":"171","chip_time":"00:50:54","gender":"Male","finish_time":"00:51:40","club":null},{"rank":"193","bib":"2058","first_name":"Jacqueline","last_name":"Sager","gender_pos":"22","chip_time":"00:51:20","gender":"Female","finish_time":"00:51:40","club":"Accenture"},{"rank":"194","bib":"2264","first_name":"Tracey","last_name":"Cliffe","gender_pos":"23","chip_time":"00:51:13","gender":"Female","finish_time":"00:51:41","club":null},{"rank":"195","bib":"1002","first_name":"Nick","last_name":"Martin","gender_pos":"172","chip_time":"00:51:08","gender":"Male","finish_time":"00:51:42","club":"Straight Outta Crompton"},{"rank":"196","bib":"885","first_name":"Gareth","last_name":"Finlay","gender_pos":"173","chip_time":"00:51:36","gender":"Male","finish_time":"00:51:42","club":null},{"rank":"197","bib":"1373","first_name":"Joe","last_name":"Ridge","gender_pos":"174","chip_time":"00:51:09","gender":"Male","finish_time":"00:51:43","club":"Run Wild Mcr"},{"rank":"198","bib":"2277","first_name":"Paul","last_name":"Lomas","gender_pos":"175","chip_time":"00:50:59","gender":"Male","finish_time":"00:51:44","club":null},{"rank":"199","bib":"1031","first_name":"Laura","last_name":"Jones","gender_pos":"24","chip_time":"00:51:05","gender":"Female","finish_time":"00:51:46","club":"Warby'S Warriors"},{"rank":"200","bib":"856","first_name":"Jonathan","last_name":"Culf","gender_pos":"176","chip_time":"00:51:41","gender":"Male","finish_time":"00:51:50","club":null},{"rank":"201","bib":"1469","first_name":"Liam","last_name":"Round","gender_pos":"177","chip_time":"00:51:50","gender":"Male","finish_time":"00:51:51","club":null},{"rank":"202","bib":"2370","first_name":"Dan","last_name":"Watson","gender_pos":"178","chip_time":"00:51:25","gender":"Male","finish_time":"00:51:54","club":"Roger Bannister'S Long Lost Co"},{"rank":"203","bib":"1349","first_name":"Kate","last_name":"Irvine","gender_pos":"25","chip_time":"00:51:33","gender":"Female","finish_time":"00:51:55","club":null},{"rank":"204","bib":"2444","first_name":"Stephen","last_name":"Wallace","gender_pos":"179","chip_time":"00:51:22","gender":"Male","finish_time":"00:51:56","club":"Team Kratos"},{"rank":"205","bib":"816","first_name":"Jessica","last_name":"Katsouris","gender_pos":"26","chip_time":"00:51:58","gender":"Female","finish_time":"00:51:59","club":null},{"rank":"206","bib":"1150","first_name":"Ellie","last_name":"Foster","gender_pos":"27","chip_time":"00:51:50","gender":"Female","finish_time":"00:52:00","club":null},{"rank":"207","bib":"1151","first_name":"Kenji","last_name":"Crompton","gender_pos":"180","chip_time":"00:51:50","gender":"Male","finish_time":"00:52:00","club":null},{"rank":"208","bib":"1022","first_name":"Michael","last_name":"Clark","gender_pos":"181","chip_time":"00:51:31","gender":"Male","finish_time":"00:52:12","club":"Top Run"},{"rank":"209","bib":"1023","first_name":"David","last_name":"Eames","gender_pos":"182","chip_time":"00:51:32","gender":"Male","finish_time":"00:52:12","club":"Top Run"},{"rank":"210","bib":"751","first_name":"Jo\u00e6o","last_name":"Venes","gender_pos":"183","chip_time":"00:52:03","gender":"Male","finish_time":"00:52:13","club":null},{"rank":"211","bib":"845","first_name":"Kieran","last_name":"Maguire","gender_pos":"184","chip_time":"00:51:54","gender":"Male","finish_time":"00:52:14","club":null},{"rank":"212","bib":"739","first_name":"Pedro","last_name":"Nogueira","gender_pos":"185","chip_time":"00:52:08","gender":"Male","finish_time":"00:52:23","club":null},{"rank":"213","bib":"2015","first_name":"James","last_name":"Greenhow","gender_pos":"186","chip_time":"00:52:15","gender":"Male","finish_time":"00:52:34","club":null},{"rank":"214","bib":"2458","first_name":"Marek","last_name":"Krata","gender_pos":"187","chip_time":"00:52:28","gender":"Male","finish_time":"00:52:53","club":null},{"rank":"215","bib":"736","first_name":"Julie","last_name":"Livingstone","gender_pos":"28","chip_time":"00:52:35","gender":"Female","finish_time":"00:52:53","club":null},{"rank":"216","bib":"764","first_name":"Chris","last_name":"Pye","gender_pos":"188","chip_time":"00:52:32","gender":"Male","finish_time":"00:52:58","club":null},{"rank":"217","bib":"826","first_name":"Philip","last_name":"McKiernan","gender_pos":"189","chip_time":"00:53:05","gender":"Male","finish_time":"00:53:08","club":null},{"rank":"218","bib":"835","first_name":"Marcus","last_name":"Fieldgate","gender_pos":"190","chip_time":"00:52:54","gender":"Male","finish_time":"00:53:19","club":null},{"rank":"219","bib":"860","first_name":"Victoria","last_name":"Armitage","gender_pos":"29","chip_time":"00:53:10","gender":"Female","finish_time":"00:53:24","club":null},{"rank":"220","bib":"1351","first_name":"Laura","last_name":"Brown","gender_pos":"30","chip_time":"00:53:22","gender":"Female","finish_time":"00:53:32","club":null},{"rank":"221","bib":"793","first_name":"Rachel","last_name":"Lee","gender_pos":"31","chip_time":"00:53:28","gender":"Female","finish_time":"00:53:35","club":null},{"rank":"222","bib":"2452","first_name":"Adam","last_name":"Balcombe","gender_pos":"191","chip_time":"00:53:10","gender":"Male","finish_time":"00:53:37","club":null},{"rank":"223","bib":"913","first_name":"Jacqui","last_name":"Baines","gender_pos":"32","chip_time":"00:53:20","gender":"Female","finish_time":"00:53:47","club":null},{"rank":"224","bib":"1360","first_name":"Robert","last_name":"Woolvin","gender_pos":"192","chip_time":"00:53:49","gender":"Male","finish_time":"00:53:50","club":null},{"rank":"225","bib":"933","first_name":"Rebecca","last_name":"Tennant","gender_pos":"33","chip_time":"00:53:24","gender":"Female","finish_time":"00:53:50","club":"#Teams23"},{"rank":"226","bib":"934","first_name":"Jill","last_name":"Kirby","gender_pos":"34","chip_time":"00:53:25","gender":"Female","finish_time":"00:53:51","club":"#Teams23"},{"rank":"227","bib":"777","first_name":"Fernando","last_name":"Guzman","gender_pos":"193","chip_time":"00:53:09","gender":"Male","finish_time":"00:53:54","club":null},{"rank":"228","bib":"787","first_name":"Christobel","last_name":"Heginbotham","gender_pos":"35","chip_time":"00:53:36","gender":"Female","finish_time":"00:53:55","club":null},{"rank":"229","bib":"854","first_name":"Ciara","last_name":"McKay","gender_pos":"36","chip_time":"00:53:40","gender":"Female","finish_time":"00:54:01","club":null},{"rank":"230","bib":"1474","first_name":"Philip","last_name":"Doherty","gender_pos":"194","chip_time":"00:53:44","gender":"Male","finish_time":"00:54:01","club":null},{"rank":"231","bib":"774","first_name":"Andrew","last_name":"Garcia Cox","gender_pos":"195","chip_time":"00:54:00","gender":"Male","finish_time":"00:54:02","club":null},{"rank":"232","bib":"1336","first_name":"David","last_name":"Thomas","gender_pos":"196","chip_time":"00:53:39","gender":"Male","finish_time":"00:54:06","club":null},{"rank":"233","bib":"911","first_name":"Jenny","last_name":"McCarthy","gender_pos":"37","chip_time":"00:54:01","gender":"Female","finish_time":"00:54:06","club":null},{"rank":"234","bib":"912","first_name":"David","last_name":"Haworth","gender_pos":"197","chip_time":"00:54:00","gender":"Male","finish_time":"00:54:06","club":null},{"rank":"235","bib":"908","first_name":"Ben","last_name":"Devall","gender_pos":"198","chip_time":"00:53:28","gender":"Male","finish_time":"00:54:06","club":null},{"rank":"236","bib":"1329","first_name":"Alex","last_name":"Toft","gender_pos":"199","chip_time":"00:54:05","gender":"Male","finish_time":"00:54:06","club":null},{"rank":"237","bib":"2461","first_name":"Henry","last_name":"Whelan","gender_pos":"200","chip_time":"00:54:06","gender":"Male","finish_time":"00:54:08","club":null},{"rank":"238","bib":"2276","first_name":"Tristan","last_name":"Kingsley","gender_pos":"201","chip_time":"00:53:30","gender":"Male","finish_time":"00:54:13","club":null},{"rank":"239","bib":"725","first_name":"Dave","last_name":"Davies","gender_pos":"202","chip_time":"00:53:46","gender":"Male","finish_time":"00:54:16","club":null},{"rank":"240","bib":"2407","first_name":"Teresa","last_name":"Banks","gender_pos":"38","chip_time":"00:53:50","gender":"Female","finish_time":"00:54:22","club":null},{"rank":"241","bib":"700","first_name":"Patrick","last_name":"Morgan","gender_pos":"203","chip_time":"00:54:00","gender":"Male","finish_time":"00:54:23","club":null},{"rank":"242","bib":"1014","first_name":"Phil","last_name":"Duffy","gender_pos":"204","chip_time":"00:54:28","gender":"Male","finish_time":"00:54:35","club":"Team Squire Pb"},{"rank":"243","bib":"2046","first_name":"Gareth","last_name":"French","gender_pos":"205","chip_time":"00:54:20","gender":"Male","finish_time":"00:54:37","club":null},{"rank":"244","bib":"2443","first_name":"Paul","last_name":"Wilson","gender_pos":"206","chip_time":"00:54:09","gender":"Male","finish_time":"00:54:44","club":"Team Kratos"},{"rank":"245","bib":"855","first_name":"Scott","last_name":"Wilson","gender_pos":"207","chip_time":"00:54:18","gender":"Male","finish_time":"00:54:49","club":null},{"rank":"246","bib":"2456","first_name":"Ian","last_name":"Williamson","gender_pos":"208","chip_time":"00:54:23","gender":"Male","finish_time":"00:54:57","club":null},{"rank":"247","bib":"1479","first_name":"Sarah","last_name":"Bulmer","gender_pos":"39","chip_time":"00:54:44","gender":"Female","finish_time":"00:54:58","club":"Breakfast Club"},{"rank":"248","bib":"977","first_name":"Matthew","last_name":"Dines","gender_pos":"209","chip_time":"00:54:44","gender":"Male","finish_time":"00:54:58","club":"Breakfast Club"},{"rank":"249","bib":"982","first_name":"Emma","last_name":"Reeves","gender_pos":"40","chip_time":"00:54:52","gender":"Female","finish_time":"00:55:01","club":"Cale Green Runners"},{"rank":"250","bib":"1366","first_name":"Tim","last_name":"Buckingham","gender_pos":"210","chip_time":"00:54:49","gender":"Male","finish_time":"00:55:05","club":null},{"rank":"251","bib":"2420","first_name":"Richard","last_name":"Todd","gender_pos":"211","chip_time":"00:54:33","gender":"Male","finish_time":"00:55:05","club":null},{"rank":"252","bib":"1375","first_name":"Fred","last_name":"Robertshaw","gender_pos":"212","chip_time":"00:54:48","gender":"Male","finish_time":"00:55:06","club":"Tace"},{"rank":"253","bib":"884","first_name":"Beth","last_name":"Hughes","gender_pos":"41","chip_time":"00:54:51","gender":"Female","finish_time":"00:55:08","club":null},{"rank":"254","bib":"838","first_name":"Katy","last_name":"Elsom","gender_pos":"42","chip_time":"00:54:57","gender":"Female","finish_time":"00:55:11","club":null},{"rank":"255","bib":"686","first_name":"Grace","last_name":"Rigby","gender_pos":"43","chip_time":"00:54:36","gender":"Female","finish_time":"00:55:12","club":null},{"rank":"256","bib":"1338","first_name":"Elisa","last_name":"Ellis","gender_pos":"44","chip_time":"00:54:50","gender":"Female","finish_time":"00:55:12","club":null},{"rank":"257","bib":"965","first_name":"Andrew","last_name":"Crossley","gender_pos":"213","chip_time":"00:54:24","gender":"Male","finish_time":"00:55:13","club":"Bolton Bulls"},{"rank":"258","bib":"2448","first_name":"Crispen","last_name":"Sachikonye","gender_pos":"214","chip_time":"00:55:10","gender":"Male","finish_time":"00:55:14","club":null},{"rank":"259","bib":"698","first_name":"Caroline","last_name":"Bauch","gender_pos":"45","chip_time":"00:55:10","gender":"Female","finish_time":"00:55:14","club":null},{"rank":"260","bib":"721","first_name":"Alan","last_name":"Boyle","gender_pos":"215","chip_time":"00:54:53","gender":"Male","finish_time":"00:55:15","club":null},{"rank":"261","bib":"1457","first_name":"Tim","last_name":"Holland","gender_pos":"216","chip_time":"00:54:49","gender":"Male","finish_time":"00:55:15","club":null},{"rank":"262","bib":"694","first_name":"Samantha","last_name":"Topping","gender_pos":"46","chip_time":"00:55:02","gender":"Female","finish_time":"00:55:16","club":null},{"rank":"263","bib":"762","first_name":"Lisa","last_name":"Elliot","gender_pos":"47","chip_time":"00:55:04","gender":"Female","finish_time":"00:55:17","club":null},{"rank":"264","bib":"798","first_name":"Charlotte","last_name":"Rawcliffe","gender_pos":"48","chip_time":"00:55:04","gender":"Female","finish_time":"00:55:17","club":null},{"rank":"265","bib":"899","first_name":"Ruth","last_name":"Fearn","gender_pos":"49","chip_time":"00:54:55","gender":"Female","finish_time":"00:55:19","club":null},{"rank":"266","bib":"962","first_name":"Mark","last_name":"Ward","gender_pos":"217","chip_time":"00:54:56","gender":"Male","finish_time":"00:55:20","club":"BMF Manchester"},{"rank":"267","bib":"970","first_name":"Andrew","last_name":"Ramsbottom","gender_pos":"218","chip_time":"00:54:58","gender":"Male","finish_time":"00:55:22","club":"Bolton Bulls"},{"rank":"268","bib":"2441","first_name":"Dennis","last_name":"Yarwood","gender_pos":"219","chip_time":"00:54:51","gender":"Male","finish_time":"00:55:26","club":"Team Kratos"},{"rank":"269","bib":"1454","first_name":"Jimmy","last_name":"Highton","gender_pos":"220","chip_time":"00:54:49","gender":"Male","finish_time":"00:55:27","club":null},{"rank":"270","bib":"1453","first_name":"Cemlyn","last_name":"Hicks","gender_pos":"221","chip_time":"00:54:49","gender":"Male","finish_time":"00:55:27","club":null},{"rank":"271","bib":"737","first_name":"Rebecca","last_name":"Massey","gender_pos":"50","chip_time":"00:55:27","gender":"Female","finish_time":"00:55:27","club":null},{"rank":"272","bib":"1035","first_name":"Danielle","last_name":"Corbett","gender_pos":"51","chip_time":"00:54:45","gender":"Female","finish_time":"00:55:27","club":"Warby'S Warriors"},{"rank":"273","bib":"1452","first_name":"George","last_name":"Auckland","gender_pos":"222","chip_time":"00:54:50","gender":"Male","finish_time":"00:55:28","club":null},{"rank":"274","bib":"789","first_name":"Donna","last_name":"Hinsley","gender_pos":"52","chip_time":"00:55:28","gender":"Female","finish_time":"00:55:28","club":null},{"rank":"275","bib":"738","first_name":"Rick","last_name":"Mills","gender_pos":"223","chip_time":"00:54:50","gender":"Male","finish_time":"00:55:29","club":null},{"rank":"276","bib":"782","first_name":"Stephanie","last_name":"Challoner","gender_pos":"53","chip_time":"00:55:30","gender":"Female","finish_time":"00:55:30","club":null},{"rank":"277","bib":"2463","first_name":"Nikie","last_name":"Arthurs","gender_pos":"54","chip_time":"00:55:13","gender":"Female","finish_time":"00:55:31","club":null},{"rank":"278","bib":"2450","first_name":"Emma","last_name":"Wootton","gender_pos":"55","chip_time":"00:55:12","gender":"Female","finish_time":"00:55:31","club":null},{"rank":"279","bib":"1145","first_name":"Garry","last_name":"Turner","gender_pos":"224","chip_time":"00:55:08","gender":"Male","finish_time":"00:55:36","club":null},{"rank":"280","bib":"692","first_name":"Michael","last_name":"Abrahams","gender_pos":"225","chip_time":"00:55:25","gender":"Male","finish_time":"00:55:46","club":null},{"rank":"281","bib":"824","first_name":"Leanne","last_name":"McKiernan","gender_pos":"56","chip_time":"00:55:46","gender":"Female","finish_time":"00:55:50","club":null},{"rank":"282","bib":"1357","first_name":"Rhian","last_name":"James","gender_pos":"57","chip_time":"00:55:42","gender":"Female","finish_time":"00:55:51","club":null},{"rank":"283","bib":"892","first_name":"Simon","last_name":"Taylor","gender_pos":"226","chip_time":"00:55:48","gender":"Male","finish_time":"00:55:56","club":null},{"rank":"284","bib":"1154","first_name":"Claire","last_name":"Ainsworth","gender_pos":"58","chip_time":"00:55:29","gender":"Female","finish_time":"00:55:57","club":null},{"rank":"285","bib":"681","first_name":"Aimee","last_name":"Short","gender_pos":"59","chip_time":"00:55:36","gender":"Female","finish_time":"00:55:58","club":null},{"rank":"286","bib":"2432","first_name":"Colin","last_name":"Everitt","gender_pos":"227","chip_time":"00:55:51","gender":"Male","finish_time":"00:56:13","club":"Smooth Radio 10k"},{"rank":"287","bib":"2406","first_name":"Sarah","last_name":"Mills","gender_pos":"60","chip_time":"00:55:44","gender":"Female","finish_time":"00:56:15","club":null},{"rank":"288","bib":"758","first_name":"Sarah","last_name":"Bulman","gender_pos":"61","chip_time":"00:55:54","gender":"Female","finish_time":"00:56:20","club":null},{"rank":"289","bib":"815","first_name":"Sarah","last_name":"Chamney","gender_pos":"62","chip_time":"00:56:08","gender":"Female","finish_time":"00:56:31","club":null},{"rank":"290","bib":"2445","first_name":"John","last_name":"Hopkin","gender_pos":"228","chip_time":"00:56:04","gender":"Male","finish_time":"00:56:37","club":"Team Kratos"},{"rank":"291","bib":"1161","first_name":"Sam","last_name":"Denham","gender_pos":"63","chip_time":"00:56:14","gender":"Female","finish_time":"00:56:38","club":null},{"rank":"292","bib":"769","first_name":"Suzanne","last_name":"Gregory","gender_pos":"64","chip_time":"00:56:14","gender":"Female","finish_time":"00:56:39","club":null},{"rank":"293","bib":"5388","first_name":"Felipe","last_name":"Scala","gender_pos":"229","chip_time":"00:55:50","gender":"Male","finish_time":"00:56:40","club":"Astrazeneca It"},{"rank":"294","bib":"1378","first_name":"Richard","last_name":"Gordan","gender_pos":"230","chip_time":"00:56:29","gender":"Male","finish_time":"00:56:47","club":"Tace"},{"rank":"295","bib":"1045","first_name":"Les","last_name":"Gora","gender_pos":"231","chip_time":"00:55:56","gender":"Male","finish_time":"00:56:47","club":"Waters Uk - North"},{"rank":"296","bib":"952","first_name":"Peter","last_name":"Phillips","gender_pos":"232","chip_time":"00:56:27","gender":"Male","finish_time":"00:56:48","club":"Astrazeneca It"},{"rank":"297","bib":"998","first_name":"Rebecca","last_name":"Fitzpatrick","gender_pos":"65","chip_time":"00:56:11","gender":"Female","finish_time":"00:56:49","club":"Straight Outta Crompton"},{"rank":"298","bib":"1026","first_name":"Joanne","last_name":"Mitchell","gender_pos":"66","chip_time":"00:56:48","gender":"Female","finish_time":"00:56:58","club":"Under Trained & Overconfident"},{"rank":"299","bib":"766","first_name":"Jasmin","last_name":"Cooper","gender_pos":"67","chip_time":"00:56:16","gender":"Female","finish_time":"00:57:01","club":null},{"rank":"300","bib":"796","first_name":"Zoe","last_name":"Olliver","gender_pos":"68","chip_time":"00:56:44","gender":"Female","finish_time":"00:57:07","club":null},{"rank":"301","bib":"968","first_name":"Toni","last_name":"Procter","gender_pos":"69","chip_time":"00:56:46","gender":"Female","finish_time":"00:57:10","club":"Bolton Bulls"},{"rank":"302","bib":"2457","first_name":"Magdalena","last_name":"Krata","gender_pos":"70","chip_time":"00:56:54","gender":"Female","finish_time":"00:57:19","club":null},{"rank":"303","bib":"1021","first_name":"Hannah","last_name":"Edwards","gender_pos":"71","chip_time":"00:56:41","gender":"Female","finish_time":"00:57:20","club":"Top Run"},{"rank":"304","bib":"2392","first_name":"Philip","last_name":"Read","gender_pos":"233","chip_time":"00:57:02","gender":"Male","finish_time":"00:57:27","club":null},{"rank":"305","bib":"2404","first_name":"Neil","last_name":"Harrison","gender_pos":"234","chip_time":"00:56:59","gender":"Male","finish_time":"00:57:31","club":null},{"rank":"306","bib":"2027","first_name":"Beth-Louise","last_name":"Newton","gender_pos":"72","chip_time":"00:57:02","gender":"Female","finish_time":"00:57:33","club":null},{"rank":"307","bib":"2028","first_name":"Kirsten","last_name":"Waudby-Tolley","gender_pos":"73","chip_time":"00:57:02","gender":"Female","finish_time":"00:57:33","club":null},{"rank":"308","bib":"2430","first_name":"Joy","last_name":"Ong","gender_pos":"74","chip_time":"00:56:59","gender":"Female","finish_time":"00:57:34","club":"Run Wild Mcr"},{"rank":"309","bib":"2265","first_name":"Nicola","last_name":"Evans","gender_pos":"75","chip_time":"00:57:05","gender":"Female","finish_time":"00:57:34","club":null},{"rank":"310","bib":"1044","first_name":"David","last_name":"Dean","gender_pos":"235","chip_time":"00:56:53","gender":"Male","finish_time":"00:57:43","club":"Waters Uk - North"},{"rank":"311","bib":"993","first_name":"Catherine","last_name":"Dodsworth","gender_pos":"76","chip_time":"00:57:12","gender":"Female","finish_time":"00:57:43","club":"Gostannes"},{"rank":"312","bib":"760","first_name":"Vijay","last_name":"Aggarwal","gender_pos":"236","chip_time":"00:57:23","gender":"Male","finish_time":"00:57:43","club":null},{"rank":"313","bib":"2411","first_name":"Sarah","last_name":"Bennett","gender_pos":"77","chip_time":"00:57:22","gender":"Female","finish_time":"00:57:43","club":null},{"rank":"314","bib":"846","first_name":"Carrie","last_name":"Hall","gender_pos":"78","chip_time":"00:57:27","gender":"Female","finish_time":"00:57:47","club":null},{"rank":"315","bib":"675","first_name":"Ralph","last_name":"McDermott","gender_pos":"237","chip_time":"00:57:37","gender":"Male","finish_time":"00:57:50","club":null},{"rank":"316","bib":"2053","first_name":"Hamish","last_name":"McNeil","gender_pos":"238","chip_time":"00:57:30","gender":"Male","finish_time":"00:57:54","club":null},{"rank":"317","bib":"795","first_name":"Holly","last_name":"Navarro","gender_pos":"79","chip_time":"00:57:44","gender":"Female","finish_time":"00:57:59","club":null},{"rank":"318","bib":"976","first_name":"Amelia","last_name":"McVennon","gender_pos":"80","chip_time":"00:57:48","gender":"Female","finish_time":"00:58:01","club":"Breakfast Club"},{"rank":"319","bib":"1175","first_name":"Gwen","last_name":"Gawthrop","gender_pos":"81","chip_time":"00:57:42","gender":"Female","finish_time":"00:58:07","club":null},{"rank":"320","bib":"1475","first_name":"Katie","last_name":"Somerville","gender_pos":"82","chip_time":"00:57:55","gender":"Female","finish_time":"00:58:16","club":null},{"rank":"321","bib":"5405","first_name":"Alice","last_name":"Hontoya","gender_pos":"239","chip_time":"00:57:36","gender":"Male","finish_time":"00:58:19","club":null},{"rank":"322","bib":"702","first_name":"Rachel","last_name":"Hendrson","gender_pos":"83","chip_time":"00:57:42","gender":"Female","finish_time":"00:58:20","club":null},{"rank":"323","bib":"1158","first_name":"Ruby","last_name":"Weatherall","gender_pos":"84","chip_time":"00:57:39","gender":"Female","finish_time":"00:58:21","club":null},{"rank":"324","bib":"1456","first_name":"Andrew","last_name":"Lamont","gender_pos":"240","chip_time":"00:57:42","gender":"Male","finish_time":"00:58:25","club":null},{"rank":"325","bib":"1470","first_name":"Damian","last_name":"Donnelly","gender_pos":"241","chip_time":"00:58:09","gender":"Male","finish_time":"00:58:28","club":null},{"rank":"326","bib":"839","first_name":"Richard","last_name":"Simpson","gender_pos":"242","chip_time":"00:57:58","gender":"Male","finish_time":"00:58:29","club":null},{"rank":"327","bib":"752","first_name":"Georgina","last_name":"Walker","gender_pos":"85","chip_time":"00:58:09","gender":"Female","finish_time":"00:58:34","club":null},{"rank":"328","bib":"964","first_name":"Adam","last_name":"Mitchard","gender_pos":"243","chip_time":"00:58:12","gender":"Male","finish_time":"00:58:35","club":"Bolton Bulls"},{"rank":"329","bib":"2021","first_name":"Stacey","last_name":"Caffrey","gender_pos":"86","chip_time":"00:58:16","gender":"Female","finish_time":"00:58:38","club":null},{"rank":"330","bib":"664","first_name":"John","last_name":"Evans","gender_pos":"244","chip_time":"00:58:11","gender":"Male","finish_time":"00:58:38","club":null},{"rank":"331","bib":"818","first_name":"Sarah","last_name":"Potter","gender_pos":"87","chip_time":"00:58:30","gender":"Female","finish_time":"00:58:39","club":null},{"rank":"332","bib":"2400","first_name":"Carla","last_name":"Scodeller","gender_pos":"88","chip_time":"00:58:37","gender":"Female","finish_time":"00:58:40","club":null},{"rank":"333","bib":"1476","first_name":"Darren","last_name":"Goodson","gender_pos":"245","chip_time":"00:57:57","gender":"Male","finish_time":"00:58:45","club":"Astrazeneca It"},{"rank":"334","bib":"1458","first_name":"Sophie","last_name":"Diver","gender_pos":"89","chip_time":"00:58:20","gender":"Female","finish_time":"00:58:46","club":null},{"rank":"335","bib":"916","first_name":"Paul","last_name":"Rogers","gender_pos":"246","chip_time":"00:58:19","gender":"Male","finish_time":"00:58:48","club":null},{"rank":"336","bib":"2438","first_name":"Steven","last_name":"Higgins","gender_pos":"247","chip_time":"00:58:35","gender":"Male","finish_time":"00:58:58","club":"Smooth Radio 10k"},{"rank":"337","bib":"859","first_name":"Clare","last_name":"Green","gender_pos":"90","chip_time":"00:58:46","gender":"Female","finish_time":"00:59:00","club":null},{"rank":"338","bib":"875","first_name":"Rebecca","last_name":"Kenrick","gender_pos":"91","chip_time":"00:58:27","gender":"Female","finish_time":"00:59:00","club":null},{"rank":"339","bib":"2419","first_name":"Natalie","last_name":"Muir","gender_pos":"92","chip_time":"00:58:39","gender":"Female","finish_time":"00:59:02","club":null},{"rank":"340","bib":"2065","first_name":"Jessica","last_name":"Toplis","gender_pos":"93","chip_time":"00:58:35","gender":"Female","finish_time":"00:59:02","club":"Darwen Running Club"},{"rank":"341","bib":"1153","first_name":"Rebecca","last_name":"Gaskell","gender_pos":"94","chip_time":"00:58:26","gender":"Female","finish_time":"00:59:04","club":null},{"rank":"342","bib":"850","first_name":"Keith","last_name":"Tickle","gender_pos":"248","chip_time":"00:58:49","gender":"Male","finish_time":"00:59:06","club":null},{"rank":"343","bib":"900","first_name":"Nancy","last_name":"Doyle","gender_pos":"95","chip_time":"00:58:42","gender":"Female","finish_time":"00:59:07","club":null},{"rank":"344","bib":"788","first_name":"Candice","last_name":"Henry","gender_pos":"96","chip_time":"00:58:31","gender":"Female","finish_time":"00:59:08","club":null},{"rank":"345","bib":"1027","first_name":"Martin John","last_name":"Broadley","gender_pos":"249","chip_time":"00:58:59","gender":"Male","finish_time":"00:59:08","club":"Under Trained & Overconfident"},{"rank":"346","bib":"1024","first_name":"Chris","last_name":"Blackburn","gender_pos":"250","chip_time":"00:58:59","gender":"Male","finish_time":"00:59:08","club":"Under Trained & Overconfident"},{"rank":"347","bib":"836","first_name":"Jenny","last_name":"Kelly","gender_pos":"97","chip_time":"00:58:58","gender":"Female","finish_time":"00:59:12","club":null},{"rank":"348","bib":"1347","first_name":"Justine","last_name":"Vandermotten","gender_pos":"98","chip_time":"00:58:56","gender":"Female","finish_time":"00:59:13","club":null},{"rank":"349","bib":"914","first_name":"Gill","last_name":"Phazey","gender_pos":"99","chip_time":"00:58:49","gender":"Female","finish_time":"00:59:16","club":null},{"rank":"350","bib":"2387","first_name":"Mark","last_name":"Owen","gender_pos":"251","chip_time":"00:59:09","gender":"Male","finish_time":"00:59:16","club":null},{"rank":"351","bib":"834","first_name":"Dave","last_name":"Irving","gender_pos":"252","chip_time":"00:58:54","gender":"Male","finish_time":"00:59:19","club":null},{"rank":"352","bib":"1143","first_name":"Rob","last_name":"Foster","gender_pos":"253","chip_time":"00:58:43","gender":"Male","finish_time":"00:59:21","club":null},{"rank":"353","bib":"2397","first_name":"Mike","last_name":"Isherwood","gender_pos":"254","chip_time":"00:58:56","gender":"Male","finish_time":"00:59:24","club":null},{"rank":"354","bib":"2396","first_name":"William","last_name":"Armstrong","gender_pos":"255","chip_time":"00:58:57","gender":"Male","finish_time":"00:59:24","club":null},{"rank":"355","bib":"5368","first_name":"Alice","last_name":"Pinfield","gender_pos":"100","chip_time":"00:59:20","gender":"Female","finish_time":"00:59:25","club":null},{"rank":"356","bib":"2052","first_name":"Julia","last_name":"Crawford","gender_pos":"101","chip_time":"00:59:05","gender":"Female","finish_time":"00:59:31","club":null},{"rank":"357","bib":"1172","first_name":"Nicola","last_name":"Smith","gender_pos":"102","chip_time":"00:59:29","gender":"Female","finish_time":"00:59:37","club":null},{"rank":"358","bib":"2270","first_name":"Paul","last_name":"Drury","gender_pos":"256","chip_time":"00:59:32","gender":"Male","finish_time":"00:59:39","club":null},{"rank":"359","bib":"676","first_name":"Vinny","last_name":"O'Brien","gender_pos":"257","chip_time":"00:59:10","gender":"Male","finish_time":"00:59:40","club":null},{"rank":"360","bib":"772","first_name":"Vicki","last_name":"Hill","gender_pos":"103","chip_time":"00:59:40","gender":"Female","finish_time":"00:59:41","club":null},{"rank":"361","bib":"863","first_name":"Jessica","last_name":"Hodson","gender_pos":"104","chip_time":"00:59:16","gender":"Female","finish_time":"00:59:42","club":null},{"rank":"362","bib":"2062","first_name":"Chris","last_name":"Gilmartin","gender_pos":"258","chip_time":"00:59:32","gender":"Male","finish_time":"00:59:42","club":"Breakfast Club"},{"rank":"363","bib":"2032","first_name":"Emma","last_name":"Simpson","gender_pos":"105","chip_time":"00:59:37","gender":"Female","finish_time":"00:59:49","club":null},{"rank":"364","bib":"2055","first_name":"Jade","last_name":"Monaghan","gender_pos":"106","chip_time":"00:59:30","gender":"Female","finish_time":"00:59:55","club":null},{"rank":"365","bib":"2056","first_name":"Phil","last_name":"Dempster","gender_pos":"259","chip_time":"00:59:32","gender":"Male","finish_time":"00:59:58","club":null},{"rank":"366","bib":"880","first_name":"Pat","last_name":"Hesketh","gender_pos":"107","chip_time":"01:00:06","gender":"Female","finish_time":"01:00:09","club":null},{"rank":"367","bib":"2045","first_name":"Karen","last_name":"Ryan","gender_pos":"108","chip_time":"01:00:04","gender":"Female","finish_time":"01:00:09","club":null},{"rank":"368","bib":"2380","first_name":"Jess","last_name":"Pollard","gender_pos":"109","chip_time":"00:59:47","gender":"Female","finish_time":"01:00:14","club":null},{"rank":"369","bib":"936","first_name":"Amy","last_name":"Taylor","gender_pos":"110","chip_time":"00:59:55","gender":"Female","finish_time":"01:00:21","club":"#Teams23"},{"rank":"370","bib":"2386","first_name":"Christine","last_name":"Parkinson","gender_pos":"111","chip_time":"00:59:54","gender":"Female","finish_time":"01:00:22","club":null},{"rank":"371","bib":"942","first_name":"Maria","last_name":"Stafrin","gender_pos":"112","chip_time":"00:59:44","gender":"Female","finish_time":"01:00:33","club":"Astrazeneca It"},{"rank":"372","bib":"920","first_name":"Steven","last_name":"Spiller","gender_pos":"260","chip_time":"01:00:24","gender":"Male","finish_time":"01:00:34","club":null},{"rank":"373","bib":"723","first_name":"Tim","last_name":"Clarke","gender_pos":"261","chip_time":"01:00:07","gender":"Male","finish_time":"01:00:37","club":null},{"rank":"374","bib":"2371","first_name":"Coco","last_name":"De La Terre","gender_pos":"113","chip_time":"01:00:09","gender":"Female","finish_time":"01:00:39","club":"Roger Bannister'S Long Lost Co"},{"rank":"375","bib":"5380","first_name":"Richard","last_name":"Poody","gender_pos":"262","chip_time":"01:00:09","gender":"Male","finish_time":"01:00:45","club":null},{"rank":"376","bib":"943","first_name":"Catherine","last_name":"Bailey","gender_pos":"114","chip_time":"00:59:58","gender":"Female","finish_time":"01:00:46","club":"Astrazeneca It"},{"rank":"377","bib":"897","first_name":"Laura","last_name":"Copas","gender_pos":"115","chip_time":"01:00:11","gender":"Female","finish_time":"01:00:47","club":null},{"rank":"378","bib":"1450","first_name":"Josh","last_name":"Taylor","gender_pos":"263","chip_time":"01:00:55","gender":"Male","finish_time":"01:01:04","club":null},{"rank":"379","bib":"1367","first_name":"Tracey","last_name":"Sussman","gender_pos":"116","chip_time":"01:00:56","gender":"Female","finish_time":"01:01:04","club":null},{"rank":"380","bib":"1376","first_name":"James","last_name":"Massey","gender_pos":"264","chip_time":"01:00:46","gender":"Male","finish_time":"01:01:04","club":"Tace"},{"rank":"381","bib":"717","first_name":"Joanne","last_name":"Caldwell","gender_pos":"117","chip_time":"01:00:42","gender":"Female","finish_time":"01:01:12","club":null},{"rank":"382","bib":"2442","first_name":"Gisela","last_name":"Zamayoa Layrisse","gender_pos":"118","chip_time":"01:00:40","gender":"Female","finish_time":"01:01:14","club":"Team Kratos"},{"rank":"383","bib":"1334","first_name":"Catrin","last_name":"Dumont Jones","gender_pos":"119","chip_time":"01:01:14","gender":"Female","finish_time":"01:01:22","club":null},{"rank":"384","bib":"1017","first_name":"April","last_name":"Hamilton","gender_pos":"120","chip_time":"01:01:21","gender":"Female","finish_time":"01:01:28","club":"Team Squire Pb"},{"rank":"385","bib":"1018","first_name":"Julie","last_name":"Smith","gender_pos":"121","chip_time":"01:01:22","gender":"Female","finish_time":"01:01:28","club":"Team Squire Pb"},{"rank":"386","bib":"679","first_name":"Tim","last_name":"Richards","gender_pos":"265","chip_time":"01:01:14","gender":"Male","finish_time":"01:01:29","club":null},{"rank":"387","bib":"2466","first_name":"Chelsey","last_name":"Newsom","gender_pos":"122","chip_time":"01:01:08","gender":"Female","finish_time":"01:01:37","club":"Roger Bannister'S Long Lost Co"},{"rank":"388","bib":"807","first_name":"John","last_name":"Blackburn","gender_pos":"266","chip_time":"01:01:23","gender":"Male","finish_time":"01:01:45","club":null},{"rank":"389","bib":"929","first_name":"Jenny","last_name":"Pollard","gender_pos":"123","chip_time":"01:01:33","gender":"Female","finish_time":"01:01:52","club":null},{"rank":"390","bib":"2391","first_name":"Victoria","last_name":"McRorie","gender_pos":"124","chip_time":"01:01:33","gender":"Female","finish_time":"01:01:53","club":null},{"rank":"391","bib":"938","first_name":"Adrian","last_name":"Halpenny","gender_pos":"267","chip_time":"01:01:06","gender":"Male","finish_time":"01:01:55","club":"Astrazeneca It"},{"rank":"392","bib":"881","first_name":"Mark","last_name":"Cohen","gender_pos":"268","chip_time":"01:01:24","gender":"Male","finish_time":"01:01:56","club":null},{"rank":"393","bib":"1363","first_name":"Stuart","last_name":"Radcliffe","gender_pos":"269","chip_time":"01:01:33","gender":"Male","finish_time":"01:01:59","club":null},{"rank":"394","bib":"1003","first_name":"Nathan","last_name":"Jones","gender_pos":"270","chip_time":"01:01:24","gender":"Male","finish_time":"01:02:01","club":"Straight Outta Crompton"},{"rank":"395","bib":"783","first_name":"Frances","last_name":"Clarke","gender_pos":"125","chip_time":"01:01:38","gender":"Female","finish_time":"01:02:08","club":null},{"rank":"396","bib":"2449","first_name":"Ian","last_name":"Hawksworth","gender_pos":"271","chip_time":"01:01:50","gender":"Male","finish_time":"01:02:12","club":null},{"rank":"397","bib":"792","first_name":"Sasha","last_name":"Kaufman","gender_pos":"126","chip_time":"01:02:16","gender":"Female","finish_time":"01:02:19","club":null},{"rank":"398","bib":"1008","first_name":"Nikki","last_name":"Bylo","gender_pos":"127","chip_time":"01:02:04","gender":"Female","finish_time":"01:02:20","club":"Team B"},{"rank":"399","bib":"754","first_name":"Chris","last_name":"Woods","gender_pos":"272","chip_time":"01:02:17","gender":"Male","finish_time":"01:02:22","club":null},{"rank":"400","bib":"665","first_name":"Andrea","last_name":"Carter","gender_pos":"128","chip_time":"01:02:17","gender":"Female","finish_time":"01:02:23","club":null},{"rank":"401","bib":"722","first_name":"Siana","last_name":"Boyle","gender_pos":"129","chip_time":"01:01:50","gender":"Female","finish_time":"01:02:25","club":null},{"rank":"402","bib":"922","first_name":"John","last_name":"Atkinson","gender_pos":"273","chip_time":"01:01:56","gender":"Male","finish_time":"01:02:29","club":null},{"rank":"403","bib":"1137","first_name":"Andrew","last_name":"Greaves","gender_pos":"274","chip_time":"01:02:13","gender":"Male","finish_time":"01:02:30","club":null},{"rank":"404","bib":"2274","first_name":"Angela","last_name":"Ellam","gender_pos":"130","chip_time":"01:02:14","gender":"Female","finish_time":"01:02:32","club":null},{"rank":"405","bib":"678","first_name":"Theresa","last_name":"Rayner","gender_pos":"131","chip_time":"01:02:13","gender":"Female","finish_time":"01:02:48","club":null},{"rank":"406","bib":"1138","first_name":"Amanda","last_name":"Richardson","gender_pos":"132","chip_time":"01:02:35","gender":"Female","finish_time":"01:03:15","club":null},{"rank":"407","bib":"905","first_name":"Karen","last_name":"Marshall","gender_pos":"133","chip_time":"01:02:44","gender":"Female","finish_time":"01:03:16","club":null},{"rank":"408","bib":"2261","first_name":"Kathryn","last_name":"Hughes","gender_pos":"134","chip_time":"01:03:05","gender":"Female","finish_time":"01:03:16","club":null},{"rank":"409","bib":"902","first_name":"Amanda","last_name":"Greenwood","gender_pos":"135","chip_time":"01:02:44","gender":"Female","finish_time":"01:03:16","club":null},{"rank":"410","bib":"2047","first_name":"Joanna","last_name":"Shearn","gender_pos":"136","chip_time":"01:03:13","gender":"Female","finish_time":"01:03:25","club":null},{"rank":"411","bib":"2408","first_name":"Jennifer","last_name":"Smith","gender_pos":"137","chip_time":"01:03:17","gender":"Female","finish_time":"01:03:28","club":null},{"rank":"412","bib":"978","first_name":"Anna-Jane","last_name":"Hunter","gender_pos":"138","chip_time":"01:03:23","gender":"Female","finish_time":"01:03:33","club":"Breakfast Club"},{"rank":"413","bib":"2060","first_name":"Miriam","last_name":"Allcott","gender_pos":"139","chip_time":"01:03:12","gender":"Female","finish_time":"01:03:33","club":"Accenture"},{"rank":"414","bib":"2266","first_name":"Tommy","last_name":"Brown","gender_pos":"275","chip_time":"01:03:17","gender":"Male","finish_time":"01:03:34","club":null},{"rank":"415","bib":"953","first_name":"Stephen","last_name":"Hazlitt","gender_pos":"276","chip_time":"01:02:50","gender":"Male","finish_time":"01:03:34","club":"Astrazeneca It"},{"rank":"416","bib":"1016","first_name":"Roia","last_name":"McHugh","gender_pos":"140","chip_time":"01:03:30","gender":"Female","finish_time":"01:03:37","club":"Team Squire Pb"},{"rank":"417","bib":"688","first_name":"Clare","last_name":"Pennington","gender_pos":"141","chip_time":"01:03:10","gender":"Female","finish_time":"01:03:42","club":null},{"rank":"418","bib":"690","first_name":"Nicola","last_name":"Almond","gender_pos":"142","chip_time":"01:03:10","gender":"Female","finish_time":"01:03:42","club":null},{"rank":"419","bib":"1377","first_name":"Nigel","last_name":"Griffiths","gender_pos":"277","chip_time":"01:03:41","gender":"Male","finish_time":"01:03:42","club":"Tace"},{"rank":"420","bib":"747","first_name":"Brenda","last_name":"Spotswood","gender_pos":"143","chip_time":"01:03:02","gender":"Female","finish_time":"01:03:45","club":null},{"rank":"421","bib":"828","first_name":"Grace","last_name":"Lees","gender_pos":"144","chip_time":"01:03:36","gender":"Female","finish_time":"01:03:48","club":null},{"rank":"422","bib":"1345","first_name":"John","last_name":"Crossland","gender_pos":"278","chip_time":"01:03:33","gender":"Male","finish_time":"01:03:53","club":null},{"rank":"423","bib":"1472","first_name":"Caroline","last_name":"Owen","gender_pos":"145","chip_time":"01:03:14","gender":"Female","finish_time":"01:03:55","club":null},{"rank":"424","bib":"852","first_name":"Vicky","last_name":"Tansley","gender_pos":"146","chip_time":"01:03:41","gender":"Female","finish_time":"01:03:56","club":null},{"rank":"425","bib":"719","first_name":"Terrie","last_name":"Blammon","gender_pos":"147","chip_time":"01:03:20","gender":"Female","finish_time":"01:04:03","club":null},{"rank":"426","bib":"682","first_name":"Aga","last_name":"Szymanska","gender_pos":"148","chip_time":"01:03:53","gender":"Female","finish_time":"01:04:10","club":null},{"rank":"427","bib":"2424","first_name":"Joanna","last_name":"Davies","gender_pos":"149","chip_time":"01:04:09","gender":"Female","finish_time":"01:04:19","club":"Cale Green Runners"},{"rank":"428","bib":"981","first_name":"Joanne","last_name":"Morley","gender_pos":"150","chip_time":"01:04:10","gender":"Female","finish_time":"01:04:19","club":"Cale Green Runners"},{"rank":"429","bib":"1155","first_name":"Andrew","last_name":"Hall","gender_pos":"279","chip_time":"01:03:57","gender":"Male","finish_time":"01:04:29","club":null},{"rank":"430","bib":"771","first_name":"Shirley","last_name":"Hall","gender_pos":"151","chip_time":"01:03:56","gender":"Female","finish_time":"01:04:29","club":null},{"rank":"431","bib":"918","first_name":"Holly","last_name":"Nettle","gender_pos":"152","chip_time":"01:04:11","gender":"Female","finish_time":"01:04:33","club":null},{"rank":"432","bib":"921","first_name":"Jim","last_name":"Nettle","gender_pos":"280","chip_time":"01:04:11","gender":"Male","finish_time":"01:04:33","club":null},{"rank":"433","bib":"1174","first_name":"Helen","last_name":"Bridgett","gender_pos":"153","chip_time":"01:04:49","gender":"Female","finish_time":"01:05:00","club":null},{"rank":"434","bib":"2040","first_name":"Eliana","last_name":"Muir","gender_pos":"154","chip_time":"01:04:43","gender":"Female","finish_time":"01:05:05","club":null},{"rank":"435","bib":"2429","first_name":"Daniel","last_name":"Ellis","gender_pos":"281","chip_time":"01:04:29","gender":"Male","finish_time":"01:05:06","club":"Run Wild Mcr"},{"rank":"436","bib":"2039","first_name":"Luz","last_name":"Muir","gender_pos":"155","chip_time":"01:04:43","gender":"Female","finish_time":"01:05:06","club":null},{"rank":"437","bib":"746","first_name":"Eithne","last_name":"Spillane","gender_pos":"156","chip_time":"01:04:27","gender":"Female","finish_time":"01:05:08","club":null},{"rank":"438","bib":"768","first_name":"Laura","last_name":"Doherty","gender_pos":"157","chip_time":"01:04:51","gender":"Female","finish_time":"01:05:10","club":null},{"rank":"439","bib":"1007","first_name":"Daniel","last_name":"Bylo","gender_pos":"282","chip_time":"01:04:56","gender":"Male","finish_time":"01:05:11","club":"Team B"},{"rank":"440","bib":"2059","first_name":"Malcolm","last_name":"Ritchie","gender_pos":"283","chip_time":"01:04:51","gender":"Male","finish_time":"01:05:11","club":"Accenture"},{"rank":"441","bib":"1465","first_name":"Michelle","last_name":"Sileck-Ainsley","gender_pos":"158","chip_time":"01:04:41","gender":"Female","finish_time":"01:05:25","club":null},{"rank":"442","bib":"802","first_name":"Francine","last_name":"Williams","gender_pos":"159","chip_time":"01:04:51","gender":"Female","finish_time":"01:05:27","club":null},{"rank":"443","bib":"711","first_name":"Elizabeth","last_name":"Mas Hernandez","gender_pos":"160","chip_time":"01:04:47","gender":"Female","finish_time":"01:05:32","club":null},{"rank":"444","bib":"756","first_name":"Karen","last_name":"Bent","gender_pos":"161","chip_time":"01:05:14","gender":"Female","finish_time":"01:05:41","club":null},{"rank":"445","bib":"827","first_name":"Donna","last_name":"Anken","gender_pos":"162","chip_time":"01:05:28","gender":"Female","finish_time":"01:05:41","club":null},{"rank":"446","bib":"2403","first_name":"Ellie","last_name":"Wilson","gender_pos":"163","chip_time":"01:05:15","gender":"Female","finish_time":"01:05:52","club":null},{"rank":"447","bib":"765","first_name":"Jenny","last_name":"Hyde","gender_pos":"164","chip_time":"01:05:36","gender":"Female","finish_time":"01:05:59","club":null},{"rank":"448","bib":"2029","first_name":"Rachael","last_name":"Molloy","gender_pos":"165","chip_time":"01:05:38","gender":"Female","finish_time":"01:06:00","club":null},{"rank":"449","bib":"2262","first_name":"Helena","last_name":"Standring","gender_pos":"166","chip_time":"01:05:49","gender":"Female","finish_time":"01:06:01","club":null},{"rank":"450","bib":"2460","first_name":"Martin","last_name":"Richardson","gender_pos":"284","chip_time":"01:05:30","gender":"Male","finish_time":"01:06:04","club":null},{"rank":"451","bib":"2455","first_name":"Andrew","last_name":"Wilbourn","gender_pos":"285","chip_time":"01:05:29","gender":"Male","finish_time":"01:06:04","club":null},{"rank":"452","bib":"1166","first_name":"Vicci","last_name":"Lowe","gender_pos":"167","chip_time":"01:05:32","gender":"Female","finish_time":"01:06:06","club":null},{"rank":"453","bib":"1167","first_name":"Louise","last_name":"Downing","gender_pos":"168","chip_time":"01:05:33","gender":"Female","finish_time":"01:06:07","club":null},{"rank":"454","bib":"2383","first_name":"Daisy","last_name":"Wood","gender_pos":"169","chip_time":"01:06:15","gender":"Female","finish_time":"01:06:15","club":null},{"rank":"455","bib":"5373","first_name":"Natalie","last_name":"Abel","gender_pos":"170","chip_time":"01:06:11","gender":"Female","finish_time":"01:06:26","club":"Rizzorunners"},{"rank":"456","bib":"958","first_name":"Tony","last_name":"Digioia","gender_pos":"286","chip_time":"01:06:07","gender":"Male","finish_time":"01:06:28","club":"Astrazeneca It"},{"rank":"457","bib":"5370","first_name":"Lucy","last_name":"Rizzota","gender_pos":"287","chip_time":"01:06:17","gender":"Male","finish_time":"01:06:31","club":null},{"rank":"458","bib":"659","first_name":"Lee","last_name":"Maycox","gender_pos":"288","chip_time":"01:06:16","gender":"Male","finish_time":"01:06:52","club":null},{"rank":"459","bib":"5371","first_name":"Emily","last_name":"Rizzotti","gender_pos":"171","chip_time":"01:06:39","gender":"Female","finish_time":"01:06:53","club":"Rizzorunners"},{"rank":"460","bib":"848","first_name":"Chloe","last_name":"Winstanley","gender_pos":"172","chip_time":"01:06:42","gender":"Female","finish_time":"01:06:59","club":null},{"rank":"461","bib":"2425","first_name":"Jayne","last_name":"Rizzotti","gender_pos":"173","chip_time":"01:06:47","gender":"Female","finish_time":"01:07:00","club":"Rizzorunners"},{"rank":"462","bib":"5372","first_name":"Jannette","last_name":"Evans","gender_pos":"174","chip_time":"01:06:46","gender":"Female","finish_time":"01:07:00","club":"Rizzorunners"},{"rank":"463","bib":"849","first_name":"Nimisha","last_name":"Patel","gender_pos":"175","chip_time":"01:06:43","gender":"Female","finish_time":"01:07:01","club":null},{"rank":"464","bib":"4557","first_name":"Izabelle","last_name":"Lovgren","gender_pos":"176","chip_time":"01:06:58","gender":"Female","finish_time":"01:07:05","club":null},{"rank":"465","bib":"979","first_name":"Helen","last_name":"Bailey","gender_pos":"177","chip_time":"01:06:59","gender":"Female","finish_time":"01:07:09","club":"Cale Green Runners"},{"rank":"466","bib":"980","first_name":"Fiona","last_name":"Lister","gender_pos":"289","chip_time":"01:06:59","gender":"Male","finish_time":"01:07:09","club":"Cale Green Runners"},{"rank":"467","bib":"1006","first_name":"Kuldeep","last_name":"Padhiar","gender_pos":"290","chip_time":"01:06:35","gender":"Male","finish_time":"01:07:10","club":"Straight Outta Crompton"},{"rank":"468","bib":"745","first_name":"Clare","last_name":"Ryder","gender_pos":"178","chip_time":"01:07:00","gender":"Female","finish_time":"01:07:11","club":null},{"rank":"469","bib":"4558","first_name":"Nathalie","last_name":"Lovgren","gender_pos":"179","chip_time":"01:07:08","gender":"Female","finish_time":"01:07:16","club":null},{"rank":"470","bib":"728","first_name":"Amy","last_name":"Fletcher","gender_pos":"180","chip_time":"01:07:14","gender":"Female","finish_time":"01:07:24","club":null},{"rank":"471","bib":"2068","first_name":"Katie","last_name":"Livesey","gender_pos":"181","chip_time":"01:06:57","gender":"Female","finish_time":"01:07:25","club":"Darwen Running Club"},{"rank":"472","bib":"1146","first_name":"Elly","last_name":"Goodman","gender_pos":"182","chip_time":"01:07:09","gender":"Female","finish_time":"01:07:28","club":null},{"rank":"473","bib":"2372","first_name":"Laura","last_name":"Hayward","gender_pos":"183","chip_time":"01:07:06","gender":"Female","finish_time":"01:07:35","club":"Roger Bannister'S Long Lost Co"},{"rank":"474","bib":"803","first_name":"John","last_name":"Bray","gender_pos":"291","chip_time":"01:06:50","gender":"Male","finish_time":"01:07:36","club":null},{"rank":"475","bib":"2431","first_name":"Claire","last_name":"Treloar","gender_pos":"184","chip_time":"01:06:59","gender":"Female","finish_time":"01:07:44","club":"Smooth Radio 10k"},{"rank":"476","bib":"749","first_name":"Kim","last_name":"Taylor","gender_pos":"185","chip_time":"01:07:33","gender":"Female","finish_time":"01:07:47","club":null},{"rank":"477","bib":"4987","first_name":"David","last_name":"Blake","gender_pos":"292","chip_time":"01:06:50","gender":"Male","finish_time":"01:07:48","club":null},{"rank":"478","bib":"2390","first_name":"Kate","last_name":"Widdows","gender_pos":"186","chip_time":"01:07:24","gender":"Female","finish_time":"01:07:48","club":null},{"rank":"479","bib":"878","first_name":"Nicholas","last_name":"Lynch","gender_pos":"293","chip_time":"01:07:46","gender":"Male","finish_time":"01:07:49","club":null},{"rank":"480","bib":"2043","first_name":"Sinead","last_name":"Healy","gender_pos":"187","chip_time":"01:07:43","gender":"Female","finish_time":"01:07:55","club":null},{"rank":"481","bib":"2044","first_name":"Ciara","last_name":"Kennedy","gender_pos":"188","chip_time":"01:07:45","gender":"Female","finish_time":"01:07:57","club":null},{"rank":"482","bib":"869","first_name":"Steve","last_name":"Dunlop","gender_pos":"294","chip_time":"01:07:33","gender":"Male","finish_time":"01:08:06","club":null},{"rank":"483","bib":"2030","first_name":"Julia","last_name":"Dunlop","gender_pos":"189","chip_time":"01:07:33","gender":"Female","finish_time":"01:08:06","club":null},{"rank":"484","bib":"1183","first_name":"Fiona","last_name":"Gilmartin","gender_pos":"190","chip_time":"01:08:02","gender":"Female","finish_time":"01:08:13","club":"Breakfast Club"},{"rank":"485","bib":"992","first_name":"Toni","last_name":"Phoenix","gender_pos":"191","chip_time":"01:07:57","gender":"Female","finish_time":"01:08:30","club":"Gostannes"},{"rank":"486","bib":"893","first_name":"Susanne","last_name":"Sands","gender_pos":"192","chip_time":"01:07:50","gender":"Female","finish_time":"01:08:30","club":null},{"rank":"487","bib":"946","first_name":"Tony","last_name":"Smith","gender_pos":"295","chip_time":"01:07:51","gender":"Male","finish_time":"01:08:30","club":"Astrazeneca It"},{"rank":"488","bib":"891","first_name":"Louis","last_name":"Counsell","gender_pos":"296","chip_time":"01:07:51","gender":"Male","finish_time":"01:08:30","club":null},{"rank":"489","bib":"666","first_name":"Louise","last_name":"Chaplin","gender_pos":"193","chip_time":"01:08:05","gender":"Female","finish_time":"01:08:34","club":null},{"rank":"490","bib":"990","first_name":"Rachel","last_name":"Boyle","gender_pos":"194","chip_time":"01:08:03","gender":"Female","finish_time":"01:08:36","club":"Gostannes"},{"rank":"491","bib":"713","first_name":"Victoria","last_name":"Yeend","gender_pos":"195","chip_time":"01:08:03","gender":"Female","finish_time":"01:08:39","club":null},{"rank":"492","bib":"813","first_name":"Iain","last_name":"Wilson","gender_pos":"297","chip_time":"01:07:56","gender":"Male","finish_time":"01:08:39","club":null},{"rank":"493","bib":"2436","first_name":"Joanna","last_name":"Percival","gender_pos":"196","chip_time":"01:08:22","gender":"Female","finish_time":"01:08:43","club":"Smooth Radio 10k"},{"rank":"494","bib":"1362","first_name":"Steve","last_name":"Stone","gender_pos":"298","chip_time":"01:08:08","gender":"Male","finish_time":"01:08:54","club":null},{"rank":"495","bib":"1337","first_name":"Doreen","last_name":"Stone","gender_pos":"197","chip_time":"01:08:08","gender":"Female","finish_time":"01:08:54","club":null},{"rank":"496","bib":"1455","first_name":"Paul","last_name":"McNamara","gender_pos":"299","chip_time":"01:08:13","gender":"Male","finish_time":"01:08:56","club":null},{"rank":"497","bib":"843","first_name":"Helen","last_name":"Mewes","gender_pos":"198","chip_time":"01:08:53","gender":"Female","finish_time":"01:09:00","club":null},{"rank":"498","bib":"2279","first_name":"Andrea","last_name":"Owen","gender_pos":"199","chip_time":"01:09:00","gender":"Female","finish_time":"01:09:12","club":null},{"rank":"499","bib":"2418","first_name":"Elizabeth","last_name":"Guillen","gender_pos":"200","chip_time":"01:09:30","gender":"Female","finish_time":"01:09:39","club":null},{"rank":"500","bib":"862","first_name":"Ann Marie","last_name":"Jackson","gender_pos":"201","chip_time":"01:09:22","gender":"Female","finish_time":"01:09:41","club":null},{"rank":"501","bib":"684","first_name":"Cheryl","last_name":"Wright","gender_pos":"202","chip_time":"01:09:25","gender":"Female","finish_time":"01:09:54","club":null},{"rank":"502","bib":"991","first_name":"Kathryn","last_name":"Dyson","gender_pos":"203","chip_time":"01:09:27","gender":"Female","finish_time":"01:10:00","club":"Gostannes"},{"rank":"503","bib":"654","first_name":"James","last_name":"Chadwick","gender_pos":"300","chip_time":"01:09:22","gender":"Male","finish_time":"01:10:07","club":null},{"rank":"504","bib":"986","first_name":"Simon","last_name":"Latchum","gender_pos":"301","chip_time":"01:09:51","gender":"Male","finish_time":"01:10:09","club":"Coffee Drinkers Who Run"},{"rank":"505","bib":"985","first_name":"Sammi","last_name":"Calley","gender_pos":"204","chip_time":"01:09:51","gender":"Female","finish_time":"01:10:09","club":"Coffee Drinkers Who Run"},{"rank":"506","bib":"1331","first_name":"Amy","last_name":"Eastwood","gender_pos":"205","chip_time":"01:09:43","gender":"Female","finish_time":"01:10:12","club":null},{"rank":"507","bib":"1355","first_name":"Michelle","last_name":"Pawly","gender_pos":"206","chip_time":"01:09:47","gender":"Female","finish_time":"01:10:18","club":null},{"rank":"508","bib":"983","first_name":"Laura","last_name":"Norfolk","gender_pos":"207","chip_time":"01:10:14","gender":"Female","finish_time":"01:10:31","club":"Coffee Drinkers Who Run"},{"rank":"509","bib":"988","first_name":"Sue","last_name":"Inglis","gender_pos":"208","chip_time":"01:10:16","gender":"Female","finish_time":"01:10:31","club":"Coffee Drinkers Who Run"},{"rank":"510","bib":"987","first_name":"Ann","last_name":"Stubbs","gender_pos":"209","chip_time":"01:10:15","gender":"Female","finish_time":"01:10:31","club":"Coffee Drinkers Who Run"},{"rank":"511","bib":"887","first_name":"Christopher","last_name":"Fewster","gender_pos":"302","chip_time":"01:10:36","gender":"Male","finish_time":"01:10:38","club":null},{"rank":"512","bib":"763","first_name":"Sofie","last_name":"Manners","gender_pos":"210","chip_time":"01:10:18","gender":"Female","finish_time":"01:10:38","club":null},{"rank":"513","bib":"699","first_name":"Denise","last_name":"Jordan","gender_pos":"211","chip_time":"01:10:20","gender":"Female","finish_time":"01:10:39","club":null},{"rank":"514","bib":"882","first_name":"Katie Louise","last_name":"Morley","gender_pos":"212","chip_time":"01:10:46","gender":"Female","finish_time":"01:11:07","club":null},{"rank":"515","bib":"883","first_name":"Andrea","last_name":"Martin","gender_pos":"213","chip_time":"01:10:56","gender":"Female","finish_time":"01:11:17","club":null},{"rank":"516","bib":"926","first_name":"Annie","last_name":"Owen","gender_pos":"214","chip_time":"01:10:54","gender":"Female","finish_time":"01:11:24","club":null},{"rank":"517","bib":"1030","first_name":"Louise","last_name":"Hiley","gender_pos":"215","chip_time":"01:10:52","gender":"Female","finish_time":"01:11:31","club":"Warby'S Warriors"},{"rank":"518","bib":"2066","first_name":"Paula","last_name":"Fletcher","gender_pos":"216","chip_time":"01:11:38","gender":"Female","finish_time":"01:12:07","club":"Darwen Running Club"},{"rank":"519","bib":"841","first_name":"Kerrie","last_name":"Barnes","gender_pos":"217","chip_time":"01:12:04","gender":"Female","finish_time":"01:12:11","club":null},{"rank":"520","bib":"1032","first_name":"Louise","last_name":"Daley","gender_pos":"218","chip_time":"01:11:37","gender":"Female","finish_time":"01:12:17","club":"Warby'S Warriors"},{"rank":"521","bib":"1037","first_name":"Lauren","last_name":"Murray","gender_pos":"219","chip_time":"01:11:37","gender":"Female","finish_time":"01:12:17","club":"Warby'S Warriors"},{"rank":"522","bib":"1020","first_name":"Amy","last_name":"Wells","gender_pos":"220","chip_time":"01:11:48","gender":"Female","finish_time":"01:12:27","club":"Top Run"},{"rank":"523","bib":"712","first_name":"Gogs","last_name":"Davies","gender_pos":"303","chip_time":"01:12:16","gender":"Male","finish_time":"01:12:48","club":null},{"rank":"524","bib":"2423","first_name":"Catherine","last_name":"Halpenny","gender_pos":"221","chip_time":"01:12:04","gender":"Female","finish_time":"01:12:56","club":"Astrazeneca It"},{"rank":"525","bib":"2422","first_name":"Lucy","last_name":"Pitman","gender_pos":"222","chip_time":"01:12:05","gender":"Female","finish_time":"01:12:56","club":"Astrazeneca It"},{"rank":"526","bib":"1353","first_name":"Lorri","last_name":"Butler","gender_pos":"223","chip_time":"01:12:33","gender":"Female","finish_time":"01:13:03","club":null},{"rank":"527","bib":"2064","first_name":"Shelley","last_name":"Frankland","gender_pos":"224","chip_time":"01:12:38","gender":"Female","finish_time":"01:13:07","club":"Darwen Running Club"},{"rank":"528","bib":"873","first_name":"Annette","last_name":"Fairclough","gender_pos":"225","chip_time":"01:12:36","gender":"Female","finish_time":"01:13:18","club":null},{"rank":"529","bib":"2263","first_name":"Rachel","last_name":"Whitelegg","gender_pos":"226","chip_time":"01:12:38","gender":"Female","finish_time":"01:13:18","club":null},{"rank":"530","bib":"957","first_name":"Kerrie","last_name":"Henshaw-Cox","gender_pos":"227","chip_time":"01:13:14","gender":"Female","finish_time":"01:13:38","club":"Astrazeneca It"},{"rank":"531","bib":"904","first_name":"Andrea","last_name":"Wootten","gender_pos":"228","chip_time":"01:13:08","gender":"Female","finish_time":"01:13:44","club":null},{"rank":"532","bib":"2379","first_name":"Vicky","last_name":"Corrigan","gender_pos":"229","chip_time":"01:13:36","gender":"Female","finish_time":"01:13:49","club":null},{"rank":"533","bib":"2394","first_name":"Katy","last_name":"Ellis","gender_pos":"230","chip_time":"01:13:23","gender":"Female","finish_time":"01:13:54","club":null},{"rank":"534","bib":"671","first_name":"Andrew","last_name":"Hindley","gender_pos":"304","chip_time":"01:13:48","gender":"Male","finish_time":"01:14:21","club":null},{"rank":"535","bib":"2067","first_name":"Alison","last_name":"Coupe","gender_pos":"231","chip_time":"01:14:15","gender":"Female","finish_time":"01:14:45","club":"Darwen Running Club"},{"rank":"536","bib":"2035","first_name":"Caroline","last_name":"James","gender_pos":"232","chip_time":"01:14:04","gender":"Female","finish_time":"01:14:46","club":null},{"rank":"537","bib":"2402","first_name":"Stacey","last_name":"Green","gender_pos":"233","chip_time":"01:14:39","gender":"Female","finish_time":"01:15:17","club":null},{"rank":"538","bib":"658","first_name":"Jodie","last_name":"Bennett","gender_pos":"234","chip_time":"01:14:43","gender":"Female","finish_time":"01:15:21","club":null},{"rank":"539","bib":"2451","first_name":"Julia","last_name":"Falconer-O'Regan","gender_pos":"235","chip_time":"01:16:07","gender":"Female","finish_time":"01:16:40","club":null},{"rank":"540","bib":"811","first_name":"Jo","last_name":"Ingall","gender_pos":"236","chip_time":"01:17:32","gender":"Female","finish_time":"01:17:52","club":null},{"rank":"541","bib":"819","first_name":"Kerry","last_name":"Connolly","gender_pos":"237","chip_time":"01:18:00","gender":"Female","finish_time":"01:18:28","club":null},{"rank":"542","bib":"1464","first_name":"The","last_name":"Claymaker","gender_pos":"305","chip_time":"01:18:19","gender":"Male","finish_time":"01:18:52","club":null},{"rank":"543","bib":"672","first_name":"Sonya","last_name":"Hubble","gender_pos":"238","chip_time":"01:19:35","gender":"Female","finish_time":"01:19:53","club":null},{"rank":"544","bib":"928","first_name":"Yvonne","last_name":"Bell","gender_pos":"239","chip_time":"01:19:12","gender":"Female","finish_time":"01:19:54","club":null},{"rank":"545","bib":"1178","first_name":"Brian","last_name":"Swindells","gender_pos":"306","chip_time":"01:19:12","gender":"Male","finish_time":"01:19:54","club":null},{"rank":"546","bib":"716","first_name":"Caroline","last_name":"Rigby","gender_pos":"240","chip_time":"01:19:19","gender":"Female","finish_time":"01:19:54","club":null},{"rank":"547","bib":"889","first_name":"Natalie","last_name":"Cureton","gender_pos":"241","chip_time":"01:19:31","gender":"Female","finish_time":"01:19:54","club":null},{"rank":"548","bib":"718","first_name":"Andrea","last_name":"Morgan","gender_pos":"242","chip_time":"01:20:04","gender":"Female","finish_time":"01:20:25","club":null},{"rank":"549","bib":"809","first_name":"Jen","last_name":"Houghton","gender_pos":"243","chip_time":"01:20:04","gender":"Female","finish_time":"01:20:25","club":null},{"rank":"550","bib":"1333","first_name":"Barry","last_name":"Goodman","gender_pos":"307","chip_time":"01:20:06","gender":"Male","finish_time":"01:20:29","club":null},{"rank":"551","bib":"1463","first_name":"Yeelam","last_name":"Wong","gender_pos":"244","chip_time":"01:20:24","gender":"Female","finish_time":"01:20:36","club":null},{"rank":"552","bib":"853","first_name":"Vicki","last_name":"McArdle","gender_pos":"245","chip_time":"01:23:19","gender":"Female","finish_time":"01:24:06","club":null},{"rank":"553","bib":"907","first_name":"Poppymae","last_name":"Lang","gender_pos":"246","chip_time":"01:23:53","gender":"Female","finish_time":"01:24:33","club":null},{"rank":"554","bib":"930","first_name":"Geoff","last_name":"Goodwin","gender_pos":"308","chip_time":"01:23:51","gender":"Male","finish_time":"01:24:34","club":null},{"rank":"555","bib":"830","first_name":"Lyndsey","last_name":"Leatherbarrow","gender_pos":"247","chip_time":"01:30:04","gender":"Female","finish_time":"01:30:19","club":null},{"rank":"556","bib":"971","first_name":"Gary","last_name":"Broughton","gender_pos":"309","chip_time":"01:33:31","gender":"Male","finish_time":"01:33:56","club":"Bolton Bulls"},{"rank":"557","bib":"966","first_name":"Steve","last_name":"Aston","gender_pos":"310","chip_time":"02:10:06","gender":"Male","finish_time":"02:10:46","club":"Bolton Bulls"},{"rank":"558","bib":"972","first_name":"Samantha","last_name":"Courchene","gender_pos":"248","chip_time":"02:10:05","gender":"Female","finish_time":"02:10:46","club":"Bolton Bulls"},{"rank":"559","bib":"973","first_name":"Rachel","last_name":"Oakes-Courchene","gender_pos":"249","chip_time":"02:10:06","gender":"Female","finish_time":"02:10:47","club":"Bolton Bulls"},{"rank":"560","bib":"967","first_name":"Sacha","last_name":"Aston","gender_pos":"250","chip_time":"02:10:06","gender":"Female","finish_time":"02:10:47","club":"Bolton Bulls"},{"rank":"561","bib":"1370","first_name":"Andy","last_name":"Golightly","gender_pos":"311","chip_time":"02:10:00","gender":"Male","finish_time":"02:10:48","club":"Bolton Bulls"},{"rank":"562","bib":"1182","first_name":"Leanne","last_name":"Jackson","gender_pos":"251","chip_time":"02:10:04","gender":"Female","finish_time":"02:10:48","club":"Bolton Bulls"},{"rank":"563","bib":"1181","first_name":"Michael","last_name":"Galligan","gender_pos":"312","chip_time":"02:10:02","gender":"Male","finish_time":"02:10:48","club":"Bolton Bulls"},{"rank":"564","bib":"963","first_name":"Graeme","last_name":"Lambert","gender_pos":"313","chip_time":"02:10:05","gender":"Male","finish_time":"02:10:48","club":"Bolton Bulls"},{"rank":"565","bib":"969","first_name":"Jay","last_name":"Willis","gender_pos":"314","chip_time":"02:10:07","gender":"Male","finish_time":"02:10:49","club":"Bolton Bulls"},{"rank":"566","bib":"2061","first_name":"Tom","last_name":"Eckersley","gender_pos":"315","chip_time":"02:10:00","gender":"Male","finish_time":"02:10:49","club":"Bolton Bulls"},{"rank":"567","bib":"4607","first_name":"Chris","last_name":"Oakrs-Courchene","gender_pos":"316","chip_time":"02:10:01","gender":"Male","finish_time":"02:10:51","club":"Bolton Bulls"}]}